{
"i3qsteq5ul66yvmskx6im2ln":["56kconnection","56k Connection"],
"jtsvkky6ptbvrvhkaiv3tomg":["a56kconnection","Lorem Ipsum"],
"jx2jg5uw7hv76wd3bydzjqfu":["broconagenda","✨kcon"],
"j4s54nfb55jq6aex2yxht45w":["cacosilva","KcoSilva"],
"3o7pms5hyuijkolwutxduuwc":["kcook700","Kris "],
"dzcirtjwduhniuhdmpar35qi":["kcortiz","KC Ortiz (Kind of a Chemist)"],
"hl2uyr3xhtekyuycbaxao4zn":["kcopossum","KCopossum"],
"hsynqlni2qxepg3r2m2jwuot":["kcorstel","Jack Baur"],
"i3ezoxgklf6oivzp4dy3szdp":["kcoyle","kcoyle"],
"qsiiubddi7sqst6km2bvahm5":["kconfehr","Kyle Confehr"],
"wcn7zqiltsrhmwxvk3vgoxrs":["kcoxdc","Kate Cox"],
"wnqrvuo7zhd4ojkp4t5ig66t":["kcog23","Gregor"],
"nq3uystlni5yjwl736nj7dwn":"kcoleman",
"225wyvxkb7k5tuyllcuy26lu":"kcomandich",
"wzvdplqggkiyk5ucdbskreul":"kcollins",
"7tvqudqj52o4fqhcyrpnvjoo":["kcooke321","Kyle Cooke"],
"2eyawe5xdffikdh5vepk7jib":["kcottle","K Cottle"],
"h3rbhywhoprwnzdm26is4osb":["kcooksey25","Katie Cook"],
"dd6miusnlvsg74o2vynsduwt":"kcoshaug",
"bcxzssmjw3vnamjjqdod5rei":["kcolony","KLC"],
"b46iwmfbtpotxwkzsz2c6qdo":"kcolempls",
"pmupjdfbgyibbc3datv53dxa":["kcodot","✨태셋✨"],
"ngc3to3gxl36wksb474ovxqa":"kcouvee",
"cyue37kikwfmwrnuselrcywi":"kcond",
"jdzzunwrh72dlq7qlmjtjpjf":["kcolemanwrites","Kel Coleman"],
"4nfl4h6ocwxjxq46aj2siiis":["kconnor","Kristin Connor"],
"lqw5m2eqnocir6yitid5clyx":["kco678","KCO"],
"2ipa75j5ijjgb6ztber74gdt":"kcollett",
"ps27wyzbel6q7tj55k4e7rzl":"kcoghlan",
"ixqidnksephgbcg7vcaitk4c":["kcos194","Kevin Cosgrove"],
"wmf6jv5pp54bppo5ojiapm6j":["kcon","Kevin"],
"h4vtotaabsqmobjbrko2fnsc":["kconrad","Katie (Kathryn) Conrad"],
"clpe6ll5sg4hstgb2cvjavfw":["kcollinson","Keaten Collinson"],
"23h4utdyl2usgqkol7i7jqj4":"kconley",
"6c2zhuja2luxfz7jq6yv5z32":"kcollelo",
"tnadcjj3dc25dknflluedn2s":["kcoleman956","Ken"],
"pj4vhqk2ur2ektpq4guwf7uk":["kconti","ChiTownKC"],
"pvpy4kqcfbpxhpi4wkp2qbca":"kcong",
"ehj6mskl62lo3il54uighgl2":["kco","Kwyt Corporsh Games"],
"v6dbyszfdgoidetyl4ltweoy":"kcopic",
"c4v5nuqpksu52xsdhkn2ptbf":["kcolemanfbg","Kevin Coleman"],
"jtplf3tlfecfcmekb5iaw24v":["kcoat90","Kaylynn Coates"],
"r5fr736hbzwn3vugos3r5jr4":"kcoats",
"xasvu3kaq22nqhu7xsnlnj7a":"kcoldem",
"2zwq66wkj3zv4x3tilt3pr44":["kcoutsider","Aaron Lathrop"],
"viz76a4p7ebdvsgy3hhamlvh":"kcoutova",
"bu2yrtsspcnhm6ajoz6ptul7":"kcoff",
"gps44ystmgo6njdbkjftf2pz":["kcorinealdi","Kaysha Corinealdi"],
"f2oe4xz4hiupofru3lqjb45s":["kconh","김콘"],
"rnqjjgsmponvju5zxjurityu":["kcokco","けーこ"],
"hfojmeyj6vkvdllvqnwy6tqh":["kcotton","Kim Cotton"],
"k6uskcpb3crzffomxks564bs":"kcorwin",
"ju4jo6plnhb6e2icfwzcyqf7":["kcollazo","Kim Collazo"],
"os4srpemr7nnbfeerechoejw":["kcoopergriffin","Kimberly Cooper Griffin"],
"6dhvajgelgfi4xc4fnccigbk":["kcooper","Kathleen Cooper"],
"htydgbi4gc2o4goas7yf2gav":["kcoquidam","KcoQuidam"],
"3ld5gfrkqmyhuqooyd7tzgpe":["kcoombs","Krista Coombs"],
"vdvnwpagmbfk3y7ty6xww2w7":"kcoo",
"mao3yhikpnwk43bi4xtvpncp":["kcourey","karyssa"],
"73x2zhe7wo6h5xxnlddnuj6h":"kcor",
"bta3k7rbpz7jeb3gsejnzm7w":["kconnersnd","KC"],
"vlgmukhvcupknwegtmo6hrka":["kcollies","KCollies "],
"und2n74trcmi2bvy2jtbw24z":["kcohed","durge town || c0mms open "],
"pzdz3owuenqyda7bjlw3agkg":"kconic9",
"ftlooml7me2m4zwdghylomjc":["kcolman","K Colman Courtney"],
"a3pfc7s7estcglg5xt5o34ai":["kcommejoseph","K comme Joseph"],
"5dfecmel6owukaoi4ipud5y5":["kcotto","KCO)))"],
"hev7fuoixudzz5dm46npcpap":["kcomentarista","KComentarista"],
"vd43bfm3ah2ahpqfnkrcdh4y":"kcostik",
"ruetjfxgbuv2ofej4vs63ibt":["kcorbzz","red flag redhead"],
"2bofcevllipmrsmf4yhsopz4":"kcoles",
"5hz6ruj4qdnvdxhezlpgbcan":["oreopierrot","KCOreo"],
"dekwjo2ezxcgkyp22g5ddlft":["q2kcompliant","Q "],
"hdp62ydh3z5nsxzp3aak276j":["toughtoffi1978","Neram Kcorbnekcust"]
}
