{
"i7a3fwojb3dvo3sixvil5jdl":["3103196","kashiwa"],
"jm4xnbmb6evghzagra5v6inz":["877kashnow","J.D. Wentworth"],
"hpthjaqzxcaouh4jmhr3c3a2":["1kashef","Reza Kashef"],
"zcf5qi6kbpbbn2y5woppe6ft":["3dgroovanstones","Dr Megan Kasten"],
"jghw6fygke6yhjpzrf463slg":["01kashi","Kashi"],
"kvocbejjg3yrj25tpk3gabuj":["587","Shannar de Kassal"],
"krnppi3lfd2rmuqzb6oydxqs":["89kaspbk","rafael 🍂"],
"gvqxp45as364gjrjek6mdvfl":["4v4n7g4rd3f4c3","kasey."],
"wkbafgz5snwgr77hpajjb6ez":["2kasux","2KASA-EMU."],
"e56zgetsztkyhhqxwictrofv":["9tcv0yemu1o6tll","Kashipan"],
"unsyorq4kd5etp6z33g6hgxg":["150kasu150","滓"],
"bmkse6up2ryfvg7blawdkjhh":["05kasei3","かせい👾KASEi-chan🇯🇵"],
"imttckdkggehfmysidyxraep":["7sukasa","kasa"],
"264yk2cxal6qekjce74nu5kr":["abiolahd","Abiola Ahmed-Kass"],
"tnddtkms4rwhx7ysko6g5cvm":["actus","KasiaNAFO #TeamYuri"],
"n5g2q62w42vmpxz5vrlyuchz":["adithyapkashyap","Adithya P. Kashyap"],
"5gq7ulqyws4f6izinaa3dv3l":["ahmedjankasim","Ahmedjan Kasim"],
"5j2xky35rq3us7qrc7hoatpf":["akass","Amanda Kass"],
"6fbbtyu4bhgvhhds3yy7gnlh":["akilab.io","Akira Kashima"],
"rfs7afx6ue4mknbhhpnrzkyz":["aktange","Andrea Kaston Tange"],
"viojc7n5mbfum3lsekwlcnqh":["akaskela","Aiden Kaskela MVP"],
"iuq6csz4fe3rgh6akhhtaqoo":["akira-kashihara","Akira Kashihara "],
"3m7jfgxjfwgw3vv57b7zgpy3":["akaste72","aKaste72"],
"ytkl3orqg4hnpzfd7e476wyv":["akanehoshino2","Akane Kaslana"],
"qs4e3gyoaqrnwnpfjlmp4yby":["akira03kshr","Akira Kasahara"],
"mt3hcx4axndzwyyasvnoxi54":["ali.kashani.ca","Ali Kashani"],
"45ipestq2omol43snj2jnryd":["albanakasapi","Albana Kasapi"],
"gxkydvwvxfq4yiv4355lqfs7":["alkashi","Abdallah AlKashi"],
"sdg4ykgrbg6qpa42b3lhdxvg":["alkaliapril","Kass "],
"aj2huqgbp4dvnlfb75fscbgb":["alchemyne","kass"],
"dfgdi6575txxtecnm3xaxxkk":["alisakasmer","Alisa Kasmer"],
"edecup6vdfpfo3fuqh673t75":["alphapupkast","Alpha Pup Kast"],
"tlwpsfx7c5icqkxl7um2pph6":["alphasakura","Kasugano Sakura"],
"c6vs2g2sp4dg33dhozjf3agb":["amorremanet","kass-less whisper ❤️ End OTW Racism 🖤🐉"],
"x75nwedsmmdizinrmq7lv7se":["amandakaschube","Amanda Kaschube"],
"saokvzjftyrjjmowkb7wlki6":["anupapkasook","Anupap Kasook"],
"kukzytpaoqhptfhrtdzlvydq":["angelposting","kas seraphim arc ⁂"],
"uq36ibl3v6z3jqklf7c4dlcm":["ananthk","Ananth Kasillingam"],
"bj6lw7ahnj77wgstypnikngp":["anithira","Kassandra 🌈"],
"66y33icds6f5cop3ut4g5nnn":["annakashina","Anna Kashina "],
"wweqhvr556eyncyzorbfiqys":["animated","Ted Kasparek"],
"tfve7tdskvkrzvah2pp3jti2":["annakassautzki","Anna Kassautzki"],
"fep5e5vhnvefyqcgmbmwtf7o":["anndercover","Anna Kassin"],
"kes5tz3dbz4qlidh2nzwqa5a":["andorkassian","Andor Kassian"],
"turr2kefqdga67x6lar4j6es":["anchorhowl","porto 🪷 kasen brainworms winning"],
"li6ht4mszcepk72tiies7wdh":["aqueousstar","kass"],
"du7r54lerhxvncgewp6cdco7":["arunikashyap","Aruni Kashyap"],
"3gwofhjbozkhfggun327qngd":["aryastark","Kashaf Murtaza-ish"],
"haa2k3434yd6okdsajjhtlue":["aryankasraee","Aryan Kasraee"],
"pxi7b3wui23gj4foha4wnuhd":["archerkasai","🔞Archer Kasai has a cold T_T 🔞"],
"dt2vhzelwalhi7vurhoc3bqx":["argyrisk","Argyris Kastaniotis"],
"o7g553xl2bor7yiwugxq2wu5":["arcticfox23","Kasey Price"],
"nyazazolzct6oao3gohnbpvm":["arielkasten","Ariel Kasten "],
"oxmtzplpfteeb3gt6rhnlvle":["attribot","Simon Kasper "],
"cvdxa7zy74g3xpgnmxmljmed":["auntkass","Kass Bestor"],
"aizjppdxkyzxhh62mevxftxs":["aurorapunk","Kasper ☀️"],
"yezhoa2nlculucmriruiuwdv":["avatarkasia","Kasia Brz"],
"hkn6hrt4o233h2yvbptqf4b6":["aysegulkasap","Ayşegül Kasap"],
"vdaltqfeoaxr5jhohb6fv7xr":["aycakasapoglu","Ayça Kasapoğlu"],
"xjzhgn2zfz5rfzyhe4km6u5e":["barrykash","Bharath Kashyap"],
"tfqpsvxf4ut7oaecsj6ybkac":["beccakassab","Becca Kassab"],
"no53xjguxgmccpy7fhzw4w62":["beansmcgoo","Kasen🤓"],
"w55thl3kyg6ttzm44ni2oaxm":["benjaminkaspar","Benjamin Kaspar"],
"rdonofufoiep67qv6h5diwju":["berokassimov","Bero Kassimov"],
"xjdziile4opkc5axlaanpzz7":["beatrixkaschel","Beatrix Kaschel"],
"c3ks5pnd7hg5czlj3qc43nzv":["birdcage","kasper"],
"xeji2bpuqofub2kmaet76qev":["bigbearwitch","Kassy"],
"mkhp7ujiszgziign3owoecn2":["bigjackaal","KaseyPurpleJackal"],
"zjvbt6cizmewu7f72uckqh3t":["bigkassino","Call Me Kass"],
"ldvktjkrbrjqn7llupdp4sxy":["birbkass","Kass"],
"ciskmjf6o452qbdi6vtk5vcb":["bigtimehardline","Kassie"],
"2vksx77jg4sbvqaucspcfs66":["biophysk","Kasia Tych"],
"s2w63esspumjza57legpktk3":"b-kasberger",
"wdgclmziuc7dmsncg2353cma":["bkaeser","Kassenmensch"],
"f3mlzfu7iduvh3fh7srasfia":["blackrainbow97","Kasey"],
"bnoyikt7hmjarnejtnbgvvzr":["bloodngutz","kas (real!!!!!)"],
"i7qpt2hgo4bvcrb5yyhbicu3":["blueskywebmkasteel","Marcel kasteel "],
"pfvpcv6p7bcsloufojxtfm6o":["blapii","Kass"],
"z4bssoenvimzigi5umhwirvt":["bluedaveway13","David Kassnoff"],
"vod6vv362vh24ngarpp52abi":["bombaboo","🫖 Kasamba "],
"7gkcnri2n6vv6cvbjhrzpqsx":["booklover87","Kassie"],
"qnrbphb6awrhe7wmdd6pwrmt":["brightflashes","Kassi"],
"zwtkeg7domiy6uw5iix5a4db":["brunokassel","Bruno Kassel "],
"v5btijhfc4jpy3smculz2hla":["briflemingo","Bri *Kashoku*"],
"tf7clnuolope6c63tl66dax2":["bumblekast","BumbleKast"],
"ahfq6tgjgcl33wf4n2nzgf3y":["cartoondog","kasey"],
"vjddp2q6oeoj542rdomrm5bm":["carlakaspari","carla kaspari"],
"podx5ixymwrdb2jn4hxevitl":["cameronkasky","Cameron “Ron” Kasky"],
"nnnh5o477k5qsv7loguvtuzm":["cathkastner","Cath Kastner "],
"pnrhpuhxonrlxuy5kftt7fm3":["caninebones","Kas 🎃"],
"y4qzrju6ymifixjh7b4ct6gl":["cassandrakassbooks","Cassandra Kass"],
"te4fherrwlb2p224v3uikxl3":["caskas","Kaspar Fischer"],
"kol3wkfzn5dbok5us5tww4qn":["carloskasper","Carlos Kasper "],
"ihyj3lww5wqf7sqkogpolj4i":["cdkassotis","Dr. Chris Kassotis"],
"f3zamcuw4ur66a4rrf4rl2m5":["cheek.dog","Kashra"],
"kfz2gcoy5etuarln3e46wyzt":["chriskasin","Christoph Kasinger"],
"t4oglctxbm3wjbcg5qclryta":["chemzymes","Felix Kaspar"],
"no577j4mejlaothapolqzy3b":["chrsk","kassatsu"],
"rayk3r72jlwefolpghvv7sp3":["cherished-cat","Kass ^..^"],
"l7bnmg622jgbftgkp3apeyv5":["chickhen","Kase"],
"ar2xptkaomk6rb4kiprjdroo":["chyrinnao","Mei Kastler"],
"tzl7heqftrb7wdu4lpe2a75r":["charly5719","Sara(kasmus)"],
"5efn7i3zxebchbxufcrp6wty":["chadhunkler","Chad Hunkler / Kasha Reol"],
"uvfj657cws4zbpz6khl4ivsf":["ckassor","Constance Kassor"],
"4kadzgxajbjnvoi5rpn7utqt":["ckpaire","Cécile Kastner-Paire"],
"y54spvjlhruh5oehksxroans":["clockymoder","kassette tape 🏳️‍⚧️ 📼"],
"2usipcnv2rua63irrnvfjcpg":["clutterkase.cc","kassandra"],
"mddqprnsso3fb4pzgze5mamq":["cletuskassadio","Cletus Kassadio"],
"u6gtghvx6g76d77xh52dtlh6":["cletuskasady","Cletus Kasady"],
"6u32vmoiw7tsjlkxyl2pgg56":["coinblock","MünzKasten 🎃"],
"7dmtauf2kpnw77xy62o3acnc":["coderbora","Bora Kasmer"],
"iz5f6jpo7ivjlks6swir4gd5":["codexjournalism","Codex⌬_v8.10.23🔂🌸Kasane/🌹Shionne Fan Club⌬"],
"s7evvugeplxgppf2wgxul4dl":["corrodedcoffin","kas 🌑"],
"sc4rcdbd7tv4sy5f6rfw4lys":["cotaniusjeta","Ali Kasım Çetinkaya"],
"wgtzxlzqbevmxqyk7uefnphu":["costamojan","Daniel Kasmeroglu"],
"gnaln2z4otzoon7xwutr4wbn":["courtingjester","Kasey"],
"rf5fuxwiaa7ml66wzb57bitn":["comradekangaroo","Markus Kasperczyk (pronoun comrade)"],
"qc4fzgjkxznqg5t4pbhqqgkg":["cutestprincess","Kasey Cutestprincess"],
"cgjnddfzkr2wij6i3iuolajf":["curtkasady","Curt Kasady"],
"alfmgvwfclyewc6m7ahnbjuu":["cufox","Hronos Kasper"],
"e3zocfnmqclmhsrx2opjuajs":["cyrelkin","Kasier"],
"xz5ouv6kjzm76azcmci4xlir":["cyborgparade","Dennis Kastrup"],
"2k2r7vh622pxjnibnclol6wl":["damiankastbauer","DamianKastbauer"],
"2lnzohxdi7dw7z3e7747qjnm":["dankaszeta","Dan Kaszeta. "],
"2tyajfiz6lbsxi6g3qj2q6wm":["davekasten","Dave Kasten"],
"j2pshpvaohqu3vghhvsg34ou":["darakass","Dara Kass, MD"],
"kj7z7iuz4qh3mewhj7f5cmdn":["danielkasten2","Daniel Kasten"],
"eohjcaek7hmv4m3feydwbeks":["dazaankc","Kashmir Conflict 🍁"],
"fuvwtt7p5jjrrrzqwjlaq7tb":["dangertwink","Kasa"],
"5pn6heuodld33w3dbfhsv44z":["daskashi","Kashi"],
"c47cvowgx7curla6y7okjovd":["daisyjohnson","kasey"],
"ovecjka6uvuvf4nmzdkhcpbp":["davidfa71","Dr Kastuza"],
"jwsyvpjdfxdva456nymtc7eg":["davidmantell","Kasha Varnishkes"],
"ynrhyremgovxqobc7iyjr74j":["davidkaspar3k","David Kasparek "],
"ld2bb6ddhf627qluofnjxxd5":["deunan","kassanova"],
"vzkznno62i5b2maywkwean7j":["delikizinmintikasi","Delikızınmıntıkası ✍️"],
"oo7nckdoperjkeqlvkwkuclf":["deejkashian","Deej Kashian"],
"r4bgzebggaqlgcb47o3syc6p":["dekasteloff","deKasteloff"],
"mplycfiauzf4zahygovdsf7x":["derkasinator","DerKasinator"],
"pnm74bm2wpbkq7zfn36cwczv":["demiana-kassio","Demiana Kassio"],
"fhgqtbzia4xswjxen2t4lodr":["dgaymerpupxciv","Kash Pup"],
"x5ytx75y3mequ2zaph4y4p4e":["dinosaurfort","Kass"],
"qggv3didrkxgykq5unh4xhro":["dilekkasim","Dilek Kasım"],
"hcufr6oazjr4g5ctccxm2wt5":["dkaszor","Daniel Kaszor"],
"qstx5gtztlojotssei7rlwdg":["dmkasprzak","Dani Kasprzak"],
"3kiz6nqhrdyhokgfezcovkir":["docslaw","Sam Kastner"],
"eunfpt64ospbm5tfgsxsj2rx":["dovy","Dovydas Kasparaitis"],
"qtlgztknsmtdq2zxc4mwczzq":["dogfruit01","kas"],
"trljngshm3mopxwx7myri2nw":["dominickassirra","Dominic Kassirra"],
"xvwc3kc7ql5h3oy5lhq6hzdv":["dragonix","Kassiane"],
"z4qjbvrxwnps2dkp4iswtr44":["drevin","Drevin/Kassette "],
"jmjiwybp2p6a5zvnctd4zcdd":["dreamlaurey","kasey!"],
"rpm4yy7im5eyzthwecgp4idy":["dreadfulknights","kass"],
"rze2ig5f27ozrkqm6d4ynvsm":["drasko-kascelan","Draško Kašćelan"],
"xfgvtfclmgw57kramg57dtj6":["drugstorescapel","Kas or leech"],
"k7y5bbczyslqvx2kwpjykmby":["drkassu","Jussi Kasurinen"],
"qen5bvpdum3xpyhfr7vlwlz5":["dwngradekasto","kasto"],
"vg2tdot4cjo474bensmbhb7b":["eamol","Amol Dev Kashyap "],
"m27xfizs4j6fsczm5vsq5m6a":["ebrukash","E.bru-Kash"],
"r6ir7siem6wncukmrw6vzz2g":["echtherb","Kaspar von Dreien 🐞 aka der Sohn vom Pfarrer "],
"a5ibjtmltyfetsvhoo6dcfsx":["eduardokasse","Eduardo Kasse"],
"oxrnfakr4mmdq76djnqsc6d7":["edicioneskasai","Ediciones Kasai"],
"7dg4vih36fa63zrh7lhczh7f":["edinkasia","Kasia Banas"],
"mezliqgvuuw2hco6ojctswwu":["ekasteng","Eric Kastengren"],
"rgv3smo4epqweew4olwdrp7x":["ekashouris","Eleanor Kashouris "],
"sqqkpgrgtglxau7a7eh3va3h":["ekassos","Evangelos Kassos"],
"3tf5ffaypyomp2bnmuavbmjq":["elik","Eli Kastelein "],
"zdloin2ztl4yju5jeykkw23e":["elinknips","Elins KnipsKasten"],
"xmgkhdwdasy643naffmhw7sz":["empresskassandra","Empress Kassandra"],
"sau3lsk3tgszwoce433j7nbl":["emikasumi","Emi Kasumi | Foxgirl VTuber 🏳️‍⚧️🦊"],
"jmsmtxc7mlhl5zww6wbzudsh":["emkazz","Michelle Kasprzak"],
"fdmogfxft62lw2566vp23ggp":["emendieren","Emen Dieren ❤️🖤 #Kassel #Watch"],
"mjgo2xvig3kglchmgqoqr3fu":["endlessempathy","Kasia Meyer"],
"qm3nbwyitf4dcn2xb7rm7dfk":["erinkaseda","Erin Kaseda 加世田エリン"],
"ucytgl5et7bdtmvct6ei4u5v":["esperanto","Eiji Kasahara"],
"37cdhtyvlts74i2gg3ollpmn":["evankashvi","Evan Kashvi"],
"7c4xnbpbf2kbf4oojaauv4hp":["face3enjoyer","Mimi \"Elysia\" Kaslana"],
"ec3yiruz4ukhxm4cc56lpuop":["farmerkas","kas ! 🏳️‍⚧️🌈"],
"4da3vp5i6qxgcsyftr6edjer":["fabiankaske","Fabian Kaske"],
"zadup7wqdyn3v65ohrzpgxyn":["fauxkassarole","Kassiopia"],
"us4m4umq2fvpeyc6cnggldpe":["fcknfxs","kas"],
"ovhbakgqogpt6qphtsi2qyrg":["femmywitch","Kas"],
"opk5ld3vaf5baiuzat5zdp76":["fek13","Fevzi Eren Kasimoglu "],
"vhfmrojqpyjqlrfh3ev3rmdp":["felixkasten","Felix Kasten @sptvmag"],
"5xetlx4ejitsubzx7apbqit6":["fistofthe","Kenshiro Kasumi"],
"rncin5piri3dmeq7arskuxsv":["fluffycollie","Kassi"],
"v3w2eqzov7huxdhc4sdagg6u":["fluffypuppykasey.com","Kasey"],
"h7ghzmybsx54opqfmfnsa7yg":["flamencoruby","☂️ kasa (comms open!) ⭐⭐⭐"],
"t6so4g4jbimaapa4ekh2iryc":["foldingcranes","Kasi 🍒"],
"x6xcxufmmtwakttvkmioxftz":["fraukassandra","kassandra"],
"dnlkbl5nfvg56w74varuxx3p":["frleinkassandra","Fräulein Kassandra"],
"reyk4ua2vv5jw5z7zstjwqjy":["friendlygeist","Kas"],
"ny6p3pdwmqpaih7pevrxaw6k":["frakaspar","Frank Kaspar"],
"rsdcw2xlokkd5pbvtmmi2qtl":["furballkasse","Kasse"],
"43g7i6e755hijl6arthuc3fh":["gavink","Gavin Kasdorf"],
"onm3jukznhtahrbvb7nnidmj":["gakster29","George Kassimis🦉"],
"gtn2fsxutwkdkw2v2xokjkic":["gemsfromagemini","Kasey Jones"],
"vegi5i5mcuy2h6z67x7wfliv":["gestalterhuette.de","Rouven Kasten"],
"qfjeqsogy7jzsxgmtugeepyz":["girlcum","Kas ૮ ･ ﻌ･ა 🏳️‍⚧️ ^⅄^ 🍓"],
"z4bpipxgz5yr3cxdhgvwayz2":["gigglebeast","KasparoVv"],
"qxpcasyh4qy5kfgrv7finwwd":["glitteredlights","Kass ✧*。"],
"rafeaetfjth4lljk3wmdyuyk":["glambrt","Kasi"],
"czq4q2twohqnvym6hhtn4yoj":["gobiasin","Kasper 🏳️‍🌈"],
"bobukazld5rq3mpgov3o3wn6":["goosek","Grace Kasten"],
"acvtorcgtfz346ueyjyomvyb":["gomikasu9213","GomiKasu"],
"3imhkcihuwibipijvva7ocmv":["gregkash","Greg Kash"],
"zv52l3ta2olmtqeqlnbe5bn4":["grgikau","Kasey"],
"7ff5ol64cumos6trt2ga4llh":["griffonboi","Kaspen"],
"ozowxqeoj7uobypwy2kr66fx":["harikasturi","Kasturi Hari"],
"jaxrdmkxca7fewj25hfmeb6y":["hamgutz","Kash"],
"ehztc5jv3aytiz4l542pexwz":["hanskaschper","Hans Kaschper"],
"rdpbla2h6apwcgzzrwd3rrh5":["hajimekashimo","Kashimo"],
"tjrjucyzzbbi5azq7lkgcwck":["hannokase","Hanno Kase"],
"br7xom6rurl2s64yf5vjkj7s":["headmold","Manoj Kasichainula"],
"oagh2zmsdvkmgli7fc4luiqb":["herrkaschke.com","Herr Kaschke"],
"ltotdgfj4uuii66uxy37ttan":["heatherkassner","Heather Kassner"],
"6ww56mj2rc5r5ya2etv46hee":["hek-yes","Harry Eli Kashdan"],
"zu2mtiw4qcvqabreghkubd4j":["headkase","Kasey"],
"j5u342xlvneu2vydji4kijs4":["hich-kas","Hichkas"],
"vqf7cpecawvxttisw4kd46e3":["hornedkassiel","Kass 🦇🏳️‍⚧️"],
"ut5xhxjwtgrkvchgc5u7waa4":["hotkasserole","Kass"],
"bqx53tfioynfenh3d46lcmjt":["hotlava","Kasey "],
"tbgpgsduqx4rvq7lzetbsmli":["hpkaska","Kaska"],
"czblpcxvr7rntp4azzdrarrm":["hultertilbulter","Lynn Kassandra"],
"yackehpkmbglq57nj22354og":["hunterkason","HunterKason"],
"2tel63xkegr6w2ihomazhztj":["hytus","kash / Hytus"],
"jfpkfclqaggx7zpuwyjjhezn":["hyllested","Kasper Hyllested"],
"ak3k7ac2w65n7mc223sfsvfl":["icakassethelin","IcaKasseThelin"],
"yfhu3ol7rqvfmjkiegswo75x":["idolrightssquad","Cami 💎✨ Kassa Must Debut"],
"vvdgykeqqeel4qsmg2lg3ski":["ignorekassandra","IgnoreKassandra"],
"3hgxl437h7ysbrxdj6clnyjn":["ihazrabies","Kasey Feral Smith "],
"gq6k34gnfzhup7v43tbsb53n":["iikimiaii","Kimiya Kasraeian"],
"6nvzy3zjn477a4pok7pqgzgf":["ijjk.dev","JJ Kasper"],
"ohi2xrnudescckz5bftpdk72":["ikashnitsky.phd","Ilya Kashnitsky "],
"phbbog7qmtofvuqjm2yvdqap":["ikzuri","Kass"],
"6kbbnngtnxap5no72aspnpub":["imperfectfunguy","Matt Kasson"],
"fbxfhuv6ciyibtd4yeymp5lv":["imrit","Imrit Kasapolli"],
"lni53zdrb5cupe4lochugrsl":["individuella","Kassandra"],
"yiwqjt7g6vsnsuc6srbgrvfx":["ovipositor","Kas 🚩🚩🚩🔞"],
"4da35svzrpodhpmlnw3lindz":["infinivoxsf","Allan Kaster"],
"5np72kkvjqrsbu6nzkrzahdp":["intrepidist","Kas"],
"apo3b4q7w7fk4rarkjsy6g2n":["intensivkasack","IntensivKasack"],
"fxm3qylbkcrhkjciuomxjvbk":["io-kassandra","Io Kassandra Tarabiscoté*e (sie/ihr, they/them)"],
"jdfl37jvtbqowndfmqzkljmv":["ishkash","Ish Kashi"],
"7dteyu4psn2eyrkq23f357nd":["itskasa","ItsKasa"],
"7xw5lmymrugvuutwk7lbwnhs":["itllglowonyou","Carolyn Kassnoff"],
"kdkgefn47hdvx4ruyrmljkp3":["itsamekashak","Kashak"],
"gwi34tzkzmqrfzf7rtcarz6e":["itskasspriem","cemetery.kassie"],
"wckkixabqyxfeb2dlcb2ylza":["jackiekashian","Jackie Kashian"],
"goresmhtp5c22kxsbu3phbjc":["jacques-ck","Jacques Chartier-Kastler 🇨🇵🇭🇰"],
"tdkzid32yea2whlbyzo4nc57":["jacobkasar","Jacob Kasar"],
"xzioa3lnj3sczzts6woa4rjl":["jakobkas","Jakob Kasper"],
"ncxj3mznyz3etdrtg5t6brjz":["jaydkash","Jayant Kashyap"],
"4vgsvum4bqroidxw3ssizzqd":["jckasy","JC Kasey "],
"rzwqs5oimxsczkkqeld7bwdf":["jennakass","Jenna Kass"],
"auysbdsg7omiz47ixigabxmz":["jessicaakassin","Jessica A. Kassin"],
"u44zch3f3l34xptfq253ynq2":["jens-kassner","Jens Kassner"],
"z3t5owpt6koblqrxb4zioz5s":["jeffkasanoff","Jeff Kasanoff"],
"on2bvynuy63z6i3eazverhbp":["jimkashel","Jim Kashel"],
"opxzfnhhyetld4hmu7xfuffo":["jinxremover","ten million kashinovas"],
"b2d7legjemduxlrnhnk3nsex":["jkaslovsky","Jaclyn Kaslovsky"],
"i5vjbvgojvrak74xzjhcgas5":["jkass99","Joe Kassabian "],
"iflwr3h3dexwko3vjx6iahl5":["jkbond646","Jason Kaster"],
"cskzb36jeiwmrnwlkhm3j4mo":["jkastellec","John Kastellec"],
"bulrohn43vdsafgxzdw235mt":["jkasek","Jürgen Kasek"],
"2clcvbcmzgghycvflian2lbp":["joekasey","Kasey Chatman"],
"2vs35nsjgrsyk2lwcg6lmjvz":["johka","Johannes Kast"],
"pytvohlwmek67ucsm4agfiql":["jrkasstan","Jonathan Kasstan"],
"qfpfsiehvdl7sr3uxylumtxh":["jumentokase","JumentoKase"],
"huvqeip2byoa47fpnjl2tsw4":["justsomedude","Kasey"],
"dl3oaa55ybtjh47hbunlwjtu":["junihuhn","Jun @Animefestival Kassel"],
"mfwmj67jms52gnjzmzhmfz72":["julez1985","Julez und Kassydy "],
"eltqvsv7iv7mtqinjit4q65n":["jxckfox","Frisky Kasai Foxx"],
"4bsd3kjndie24pdbw2cfjyfl":["k43124k","Kasra | کژوان"],
"2gk2de7pakjnrjbkimfch2ef":["kassemg","kassem g"],
"2kd5rb5dfmbcqzntnya7y6xr":["kasselpjc","Kassel"],
"2qrxf4kc7qu2nv2ioy7atz4t":["kaseygifford","Kasey Gifford"],
"3ougksmrt2s3xy7axnfsyv4i":["kass01","PampEnforcer / Kass "],
"4hkvhvutwsgbgl23aivvjfjm":["kashkull","میربابا "],
"4tcusyvmyoyg5gncyhkmnchi":["kasan","𝙠𝙖𝙨𝙖𝙣🖤🧡"],
"5qjhvbksz36qfg5qcs5fqte4":["kaitken","Kasey Aitken"],
"64lcy3u3n6hyjxay7zspreu3":["kaseotter","Kase"],
"6xah3yni6rnj25nr54ydrrkw":["kasteraoisii","ろむ"],
"6y5zhrnh232n7cbft6esixxx":["kasettetape","KASETTETAPE"],
"73yxea4hckxywt6alpfi53cv":["kastenfrosch","Günter Kastenfrosch (überfordert)"],
"7fj42g6hvwpf3ucbrlgukelb":["kassil","Kassil, Mechanimist Heretic"],
"a25kqnnqd7g4bvahjwz2enkh":["kashana","Kashana"],
"a7vo232jd2itxnxxr3oatn6y":["kasfel","神砂"],
"aqi4n324w4525yyvisa4gfyj":"kasmir",
"awikbqh636eq7bc54tczjjkd":["kassandra","Kassandra Peck"],
"bkgmwpe23rtiwcshhftl4tav":["kassillea","Kassillea"],
"boilhhx4hqs5rwq25vderlwd":["kassandraw","Kass 🏳️‍⚧️🛤️"],
"btf6efybgzc76ugmhblpiuqz":["kasss","Kass"],
"bwwfkohdii4utig6e2bhq23l":["kariekaski","Kari Elisabeth Kaski"],
"c73zs2wlzlp6wqzxguxhogm6":["kasiaiskasia","Kasia"],
"caqik4ci2hkzm6mk7rrmh6ed":"kasai",
"ci4jwz5rpp2lhu6vko32iqdn":["kasmolenaar","Kas Molenaar"],
"cxefvdh2dwngcqup42euotya":["kassandraoftroy","Kassandra of Troy"],
"cxvecv4hwkeb75ravbcgin6e":["kasketart","Abel the Human 💕"],
"dpsmmtgwvkotwygqq7haqcqw":["kaschewi","Federflüsterin"],
"dqepwbtpnwkfp5xta3p366wc":["kasenc","Kasen Christensen"],
"dvhr5xdxfr2gdw7u5mmot4e4":["kashyyyk","Kashyyyk #DavosSafe schools 😷 PCR for Public"],
"dyt2oczwvwahimoh5pdt66b5":["kasukadoki","千歳茶 幽時"],
"edj4k6ww5gksyl7mwepa6mmg":["kassenmeyer","Oliver M. 🌱"],
"eim4avklvab52yfensccjm74":["kashkadavr","Kashkadavr"],
"eyqfgbjcmyewkhcltszxcjmd":["kashmere","Kashmere"],
"ez7d54buux2h7usntzyn4saa":["kasseler","Thorsten"],
"fgdcvzsbosrrbj6klhxqioit":["kasra.uk","㉿"],
"fralotx76khf24rrwplpcqyu":["katjakasimatis","Katja Kasimatis"],
"g6qsjywbr2sfpachajwns7tt":["kassiopeia613","Ziska."],
"g6s6rfuwgs566ragq3mpinse":["kassn","Kassn"],
"gikru6qz3zh5yla4gu3z4o3c":["kashi","Kash"],
"glkoy6zynbiqyyzc63isplru":["kasraskki","کسـرا"],
"hb4uzvrh4xddz63zh5inveau":["kashiko-bs","かしこ"],
"hkegjezerbdvpnoakjw4qfzl":["kasim","Kasım"],
"hsy4mj3v4yilplxdxezoxxze":["kasutama","Kasu"],
"hvplwijw37b2uu4vsdv362ly":["kaseejedimaster","Casey Masterson"],
"iidgkgahyfeyrlkuhcdl2uvj":["kasmaurice","Kaseem Maurice"],
"iroo5wf3kkozpuosjfdbkj6m":["kassielle","Kas(ia)"],
"itmbmy6vogsuig6on4evlfmx":["kashannkilson","Copy McPasty, Writer"],
"jboiwgjfu5avxivy47z5ilms":["kasika","Kasika // 🏳️‍🌈"],
"jugumae7bu23rtdgwmilgaaj":["kastor","Kastor Nexus"],
"jwbakpmpy3hs3gya7aievt3c":["kasei","KASEI・KOSEI"],
"k54ef6z7t3buy7byke7t5dca":["kaspar.dog","KasparCollie"],
"k5pgn3hvob2cuqxriojey6kl":["kassiopeeia","kassiopeeia 🏳️‍🌈✨"],
"kbsvi2663c3cmgtyfaucajmz":["kasiechoochoo","Conductor Kasie  🇺🇦❤️💚"],
"klqma72itgwiqfrqmln4dg53":["kassandra68","Andreas Ludwig"],
"kykuvlytxsvszmipximnrz7e":["kashima0ko","カシマレイコ"],
"l2snp6pr5w3eelzka2k53ymy":["kasphomet","Allen"],
"lh7mya2y5qzcvtr3k47yedqy":["kasper11","Kasper11"],
"lnpatywbc6wsm3zjaikysyrq":"kascz",
"lpke3vcmub3fhdjbscrnp4a3":["kaseywllms","Kasey Wllms"],
"lzmwfgfu6fsjxc4tinvcongg":["kasan00","花閂"],
"momixskwpar2vjptnxuddh7e":["kashouri","Liam"],
"na4isjzja55ibuxaqdbxuv3d":["kaspar-stonenature","Kaspar Stonenature "],
"nekrlrqey76qrwzvdyzhzgzk":["kassiejo","Kassie Jo"],
"ntkmgew2vnq7lkpze65ffmzx":["kashhill","Kashmir Hill"],
"ntotzhottxtet75sifxbftiw":["kaseycorbit","Kasey Corbit"],
"oa36vysox66jzozwbtfbs5fv":["kastranec","kyle"],
"oatgz3cnonmdqh7zmob7xhl3":["kassian0x0","Kass / Comms Open!"],
"ob6uyiyupz57djlltcd7dz47":["kaskajessica","Kaska"],
"oedijtin2tv77vvhhjdj5ler":["kasmisdre","kas 🏳️‍⚧️"],
"ogs7eaqyxyuitndzxxesg474":["kasscabel","kass ! "],
"opwetlvn2fs4rkhlzud4yvt6":["kasmi","kasmi"],
"p2cxxijn7h2fq7z74hjq4kmz":["kasperdijk","Kasper"],
"pokgjvdasqdqgfx52uusufgv":["kassandramythos","Kassandra "],
"qfsvdyecingfr7fit2fwwz3h":["kashcat","Kash 😼"],
"qjn7rzeymyryynjpbqit7o6a":["kasparmairowitz","Kaspar - Metroidvaniac "],
"r6vy2ghfhw7znpjvjyjdcayd":["kasulke","Calvin Kasulke"],
"raauv27jklkrroaxtvq3jzft":["kassy","Kass Sakagami 🌓"],
"rbf3xq3ut2sn3finns2ixwok":["kastrullis","Ewejka "],
"rrkyrb6pxijng7eolvbdm2rb":["kasifel.gay","KasifelVT"],
"s2t36ch4ct6ljjtt2573c7wp":["kasigfuchsgoku","🦊Goku!🦊🐀Brooklyn!🐀"],
"s3oals2rjxltrvlen4zzvejz":["kasiak","Kasia "],
"sbpy3nauni3bilpl6e5lhxdj":["kaseboy-advance","kase"],
"scwp3fmvqegqaoyckaltvkkw":["kashmiri","🤍"],
"t7eim6tkwjltj7brjydqj7yd":["kaskali","Lluís"],
"ts44enwvmr7vicw67qub54gl":["kaschenke","Karsten Schenke"],
"ugpcke4fps2yvtahs33c6bbe":["kaceykasem","Kacey Kasem"],
"uzjjhc6lhru5emqggcgnh23l":["kasperskolf","Kasper The Skolf"],
"v6fxawgy2igothpkd3qcyxcq":["kasuga-iz","春日 / kasuga"],
"v6i5rl637dxymb2uqjpfmsz4":"kasstoner",
"vha7klnheqhhz7hzcmh34kra":["kastronvie","Dr Squiggles 🐇"],
"vozcmcgcefehljxbyfvsci32":["kasasagi77","kasasagi"],
"w3xnnskj5tn4xozmlv5rapkg":["kasrakeshavarz","کوه‌‌پَلاس"],
"wgpb2orkhj6kw2wzo2awuyq7":["kassassassin","Kass Assassin"],
"xagk4bfo2t57em6afxlrscph":["kashiomiart","нет ето не так 💙💛"],
"xoh5mkqnm7lquvig7p7brjvk":["kasedog","Kase"],
"yh27v7dd55aezmnorerkuf4a":["kassfrz","zZKassFrZz"],
"yyqlvskcpsk25w4hsdtfagie":["kasumi89","Kasumi89"],
"yzqfliywcadqfvqm2ktdrgm2":["kassiesharp","Kassie Withakay 🏳️‍⚧️"],
"z66oqwk76v75gaw7asnqvdyo":["kastutz","Kah Stutz"],
"za7d334qth3nvl5tnwjmcrjw":["kashprime","Kashif Pirzada, MD"],
"zjdsoe6qh3i2uthkpu6qga7n":["kafisart","Kasia ‚Kafis’ Zielińska"],
"zkwblncozfrzj5ckh6wpewtr":["kassimentz","Kassi Mentz 🏳️‍🌈"],
"zp6zmhnk6wlbrmezqazdwvqr":["kaserisu","かせりす"],
"zthszt2jqikn3dyoa5fokzhm":["kashmoneym.ink","KashMoneyMir 🔞"],
"zwzrs5pzwk25f6wihycna67o":["kaseysnow","Kasey Snow"],
"mnfygcmonysu3rgo3amjp6xd":"kasumi",
"kbbs7u3wvqbnbeybgu5et5jq":["kasper","Kasper"],
"cdi76arqcxycdpujklbtgwaa":"kaspershow",
"bfqsxmsuxx6pdnsred4jjmuz":["kasra","Kasra Hatef"],
"bajs33miwghf2pulmuckzact":["kassem","Kassem | قاسم باغر"],
"b6rynanmx55alf57mfkkergr":["kas","Kasra"],
"jfsuaxkx57p3qpfyyho2mrcn":["kasey","Kasey"],
"lznvqrhiciezjlhv2rbt5poi":["kash","Kash from #TaxGPT"],
"nvrkli6pxkp6w2gka4ulwzsg":["kasra.ingroup.social","Kasra"],
"jghsrevtupobqbwbbcrsap6d":"kasteeyo",
"666fpvoj4igrjlexwm6uhred":["kaseyc","Kasey"],
"jikfk3mliztuc7tnyrpx6bwy":["kasrak.com","Kasra Kyanzadeh"],
"wiubaxiomybtheyrjcduoibd":"kaspars",
"igqgxtxms5ivq6usexmaive7":["kasumihie","Kasumi"],
"6dfm7xnncdvndajnszlgbzlm":["kasrara","kasra"],
"7l3mcpvy7sjcb4zyo7kyzm5e":["kasrasamareh","Kasra"],
"2avnupcttvf6pyyaep22oyi5":"kasteph",
"jxxg57cpgv5ucewvlzthq7xs":["kashvi","kashvi"],
"qyro7dgrwjdvivf7zxudkje6":["kasumin","佐木カスミ"],
"sbnqfa4h4ubxq3glk6vxmgyt":["kasuken","Emanuele Bartolesi"],
"e37k2mocg7e6tnund62tmpmz":["kaslin","Kaslin Fields"],
"ugukvhac46j4n27p3el52syd":["kaszies","Kasper Steernberg"],
"3gaejdla7yeypu6w7tiw5idc":"kasama",
"txnlrfcck6uv3qj34smsn4ar":["kasper.website","Kasper Andersen"],
"ogyq5pkotuzgla434imoaedm":["kasturi","Kasturi"],
"gxysfboz4ngmd3daqxxh5sy4":["kassthefish","Dr. Kassandra Ford"],
"ei53qswkjaigrzjo76eqp65y":["kassandrakoala","Kassandra Koala"],
"2huippy3he4pmaoecyulol6c":["kassie","Kassie Epstein"],
"whsw2rz35lqp2lpnl3suxmjw":["kasimeslehichkas","Kasi Mesle Hichkas کسی مثل هیچکس"],
"beilw2vh3q6laeruyz7sucu2":["kasi3","Kasi3"],
"cnl33dcdyjuw5tkvwi7yg7pu":["kashdan","Jennifer Kashdan"],
"xl7yheruug4aii4frqlrm4kh":["kaseykourageous","Kasey "],
"rjvxp6kfi7fntvwylrrcy5pj":["kasima","Kasima"],
"l7bxlpsvhlkauj2jvityw5jw":["kasuyamofu","KasuyaMofu"],
"qpaq74qs3ra7w6y2qnwiyzp7":"kassw",
"3ib22zdmerwqzke3gxoysxby":["kastello.eu","Kastello"],
"xb5a4mpxbv3bbm5gckvoxwrh":["kaseda","銀パパ"],
"usy6q3r64dcd27baezw4etvl":"kashif",
"ehusjxureigsaji276i6b724":["kashka","Shimrit Elisar / Kashka"],
"xqiqdyihwpjnav35r6wruy34":["kastner","Erik Kastner"],
"peauihdntqe6vihqgqalqisq":["kasaya","kasaya"],
"kcqho7un7l4ppbk6v25laxz5":"kassevy",
"xvisce5yulvgvttzjd756fxi":["kasprzykmichal","Michał Kasprzyk"],
"7d5mb4xa5si2oy3hukq2o3jv":["kasraa","کَسرا"],
"6cew6vgr6gm62ibigmzhumfc":["kashioka","kashioka"],
"a46wolcuohfjarla7ev2qo2f":"kassiekassie",
"uzpcccqo2gqk2uaislwn27b2":["kasahara","Kasahara "],
"gbil2apg2feq4bs4l6lqt27f":["kaszuba","João Vitor Kaszuba"],
"wfgsrvrelf6pi3d4jpg44u4z":"kastilyo",
"fzrl2uowj5tmofeq53dzsfr5":"kase",
"hr3haqtvjjtehkijkrn2opvk":["kassadin","Kassadin"],
"64n2rxq4wdgfq6ij2bdom3iv":["kaseyaobrien","Kasey O'Brien"],
"l66fhshatnovlpppgtsyhzwy":"kastn",
"s5xi3vwpnmlam4zf2dxnp3hi":["kaseyshafsky","Kasey Shafsky"],
"vgq3ux3gj7ccuj5hbxij5law":["kashima","かしま"],
"um7rs2dmab5a4zk46twmrugx":"kashamaru",
"movogtzzwkdsoitrprkc3z4x":["kashalioness","KashaLioness"],
"peu7i7imzbdtt6gbftyrir6e":"kashelani",
"v64k7asq54jpxr3uyoircckd":["kastor.sh","Kastor"],
"vaoztml6m37npxu4lbipba24":["kasaragod","കാസറഗോഡ് "],
"nnsndlby4jrpkdd6ar2rf2vb":["kasu.me","CUPMEN/M_Kasumi"],
"mdia63sy7k2ofxsgv6w53q6c":"kasra8393",
"xrqb3v2digmajymbcftf7izj":["kashfidamo","Kashmala Fida Mohatarem"],
"7tymbbfa3bxcnzuygbk6cfz4":["kasey99","Kasey"],
"tq5wfqirotiheu35aylnplin":"kasem",
"4jofofxr2jrrp57ididrtr4o":["kasino","Vegas"],
"uwb5drawr5rgpsit2qo7qzih":["kasumikarina","カスミ•カリナ"],
"kpmbpb65a7aq3cghuklrqavu":"kasia",
"bkwmjlehy4k5wbuy2zlcyukn":"kashyap",
"xwh2wkwpsksnkvgjmkymuik3":["kassraaaaa","کسری هستم"],
"2r2psexzipbfzv3rd2v7wedh":["kashfi","Ali kashfi"],
"cppjd75fhs7wre7aehyzrc4w":["kasinbatya","Отето жизнь"],
"ybnfstj67rk4dgj4srtmioz6":["kashiba","かしば"],
"jgsogliktdzovyyo5ctyv2bj":["kass","Kass"],
"wch4rdisqct64nnzlh3vsp5v":["kasumidirect","Kasumi"],
"h62cd36kecpjvhhsbfeusaup":["kaspar","Kaspar"],
"5kqtv54jgyqyjcpxcq6mt3ai":["kasoken","Kasoken"],
"6qgh2rjz5nesdl2mdtxedlwt":["kasuy","Kasuy"],
"am2qisjdeukznffdfp3luwkg":["kasara","Kasara"],
"iqsz5vlty65mitgcgfylgxfo":"kast",
"m6mu5ctfnuzdsptzvvsbcrih":["kasjavi","Kasra"],
"mjdbjchuz43jyra6a3dj3o6k":["kasumiotome","하초"],
"mabbgpnem46wbumegu3w6c7n":["kashramli","Kash Ramli"],
"tw2hg6plzklb66vfegytzjgi":["kashiyuka.net","Motoki"],
"g3k6e4mlp7hndyjw2bnp3rpp":"kasanosita",
"q2si37z4urntmqthqijc5oaw":"kashan",
"llojak5fpuyvkqnrvvufdied":["kasi","kasimir"],
"2mald3f2xn4fo5lvbjoiipci":"kaseykirk",
"p4tn3sf4ntyktudq7462zm2n":["kasuehiro","KaSuehiro"],
"tzc5mfow36nuqfnelcjnb27b":"kasface",
"xwm7avj6pnn2a75vaoxosm73":["kassielnelson","Kassie"],
"6hy337oeodhjpsa2ezr34xdv":"kassandraseven",
"vzbsx6mat366vhahk52ctlul":["kassdog","kass dog"],
"bbungxy6zdb4ke2ofbpxp2pq":"kashishds",
"4pzdxqzt22ut6filtvgmocn5":["kasperdhansen","Kasper D Hansen"],
"s7ci2tdajwtasiatf5cz22gc":["kashtanchik","Kashtan"],
"moxrb75tvbvp4yl63isk4zky":["kasalfinley","Dawn Kasal Finley (she/her)"],
"vniukbfz7sus37w5twvxlni7":["kashli","Katelyn"],
"bud75mchbvsxhjl62fbs2rqi":"kashadoo",
"mrumiv4ma4pvtiiso2rwthis":"kassita",
"texdiysyqcbg4m5757hljlfa":["kasiwagi","かしわぎ"],
"26kem2l7fzdn3wmt22hq4lsn":"kashyapd",
"eupj7hyf344lp7kfhgoxrgtk":["kasuyarou","カスペル"],
"jwxvbqq5gp7scevjazs73kpk":"kashiwame",
"kcxb6j4qlrzeqq3ep2j4tzgo":"kassen",
"oawn3bnxcszuohuzpik2sqju":["kaspartamsalu","igrim"],
"jplnpqdhubm75uhbilklwl35":["kasimma","Kasimma"],
"wi4di5ibavfplgjicr4bcwph":["kastellan","kastellan"],
"iiobcx7y64uq7uddv26qw5oy":"kaspa",
"o2lwljir5cswpayifzmgl5by":"kashefekhak",
"3ozpueetw35gl6uremnqjsg5":"kaseywynne",
"bxumcouvunj7vcvcgzjpo6yn":"kastle",
"u3ntl5c25lnmi7qmci4jxu6w":"kasumi-i",
"7xfodeusrezbs5rcbi2mktyv":["kasu","酒粕🌾"],
"m4qah4cjnpvacuvgpcdzjglb":["kausto","Kasperi Kunnas"],
"hzoymta4chvlag7ueuq2rxys":"kashtan",
"boudorixvuikmtcoimb5qwcr":["kaszidanger","Kaszi Danger"],
"4nrpsnhszvayvvjmeatxwsss":["kassia","kassia krozser"],
"jylj4mixniaucdunntbwkwmb":["kasky","Kasky🔜MFF"],
"gjkg4jup4563vkpha4vlyx5k":"kashenj",
"fetdcy32jxnmy5ajougye6pc":"kashiwo",
"k6wtr3kf7hh63hzgaexlf75a":["kasumic","kasumic"],
"rjqtc5qtfko3r5to56l3w7au":["kaszeta","Rich Kaszeta"],
"ewgttovn6lfhxam34n6ozkbk":["kastal","jame"],
"jqk4rhztneu4vjxow5ibdb47":["kaspar-allenbach","Kaspar"],
"b5pydl5upiaxirtrhztebgyc":["kasiom","Abi"],
"3ucmnax2hsq2yqcaof7jsnzo":"kasrazarebidaki",
"ilvandrox55g35ls54r7kvki":["kassiva","кс."],
"enpliobijt4kiy7tbp2w4xeg":["kasumi2j","kasumi"],
"igcozwj6lqpqhwulzgdev2ks":"kassyfineface",
"pai5jx7r4f3z2vbacsgo7fp7":["kasdaq","Kasdaq"],
"64y2623ijtydudqel6r2oz2n":["kasrahsg","Kasra"],
"owmkccqemlmefyv4wws6rjrq":["kaseythegolden","Kasey \"Super Sketcher\" Golden"],
"l5ocjiq6xgtk6pimzkmgmigu":["ka40a","Yusuke Kashima"],
"tef7mnjfffkdgrd3miwenjfi":["kasferret","Kas, Dumb of Ass"],
"gjg2ggiwfb7fawmffloou5m2":["kassitzel","Kassi the Ninth 🐺🦉🐝"],
"bnrhzp5m5gdko2jxkm6i2uii":["kasonmane","kason_mane"],
"ufxikogdmkgigod7eng7xwxs":["kaschra","Kaschra"],
"gu4xpfzguqy4jfglkrm64iot":"kashaleedee",
"ui77gp2ee4rqgxvhniqgnajz":["kasumidoodles","Kasumi Doodles"],
"zydbujbi4dvacwsb2bhdr5xc":["kass.rip","Kass"],
"oxwhnvrycj43i2e4i4eudvrp":["kassandratlo","Kassandra O'Brien "],
"2xov4aspuzwal7qnhgk7m3u7":["kaseyi99","Kasey Ignarski"],
"nf675x4vkg7he75ak46m2zpx":"kashi0721",
"rygguhwdqvz35e2d4tqlyivz":["kasteron","Meesh Birb "],
"sl5xbnktasua2fzkctei4kd6":["kasemth","Kasem"],
"fz5444clnujhar5ayy6yh5zd":"kashmir",
"mmxmilexmlxruy74shrl5goc":"kaseylawrence",
"rhxcgwehwcy5zpqm2dvbn2qm":"kasimaria",
"4pakj74q4aawdsqmwaw4vnyw":["kashksab","کشک ساب"],
"latdkg46fmvmspyxq5crzeud":["kassaba","cassava"],
"eabysk563u5e25arkttbbto4":["kasubr","Kasu"],
"sdpc6wdau7niptmigvuubp2c":["kassandraheller","Kassandra Heller"],
"6layj6s4et33h5pze7ki4rem":["kashu","かしゅう"],
"ni2qkt2dgddosci7uf4oher7":"kasra1",
"hyape5de74oyfis3btxho5dd":"kasperkombrink",
"5e4mm3rmt4wbsvipx73f7tpn":["kas96","Kasia "],
"35qqsird33qgcanrgfwy5tyu":["kasagiwr","傘木"],
"wjx4cqb6hsddaoh63elo27ge":"kasesari",
"kxfyu4j7uxzdgcuyxsriri6e":["kas-kas","Kite/Kas-Kas"],
"eo73wea7nnykwrtmqnf7ldud":["kasiar","Not My Favourite "],
"r3wgiuhyuszjoxtnl7a5yyth":"kashkool",
"czlb3cekthuptbha7rz7ec2k":["kasutherland","KA Sutherland"],
"e2pf2hnu6c7pcvm7yymbmuq2":["kassai","lattice"],
"vfhgxj437rgg5umf42lbaasb":["kantie","Kasper"],
"baxmsarsgeyr57eigv6xesym":["kasimova","Kas ✨"],
"ubwlagouvwll6ze6z4jp7r37":["kasualkaymer","three raccoons in a librarian suit"],
"kqgqtrx73cq7b5k3yhyylw2b":"kassim2468",
"fd4b2gbh5ljytb4ptrmkakym":["kasa0809","사탕"],
"tb43p6mod6caxpjig6hmx64t":["kasperkitten","Kasper"],
"5zb7xp3xtvgiahjnzgfj7yfg":"kasperbrandt",
"yhte322yhih2hiv2xbvd36rc":"kasperk",
"7rmymyokpliucdhmz26zkije":["kaslota","безробітня мразота"],
"atyr7x4fbtwlwz32xu5teef2":"kaszek",
"6gzndt4uq7g2y2wb6zvhwwst":["kasram","Kasra Farzin"],
"pfes3fs2fve3dbfhkslrwcs2":["kashi0530","みと🐺⛩️"],
"42ub6oe5v5fp73bkozju2mw7":"kaseyo",
"uao3lj76pmnihzxdfnh2bfmg":["kassythr","cath🥀"],
"foun4dtlb3y22kiekdajkwxi":["kasparspds","Kaspars"],
"24xjpifuak5szpyhvbavli7y":["kashiwagi","柏木"],
"nxj7jstexxru3tahumlqaeqv":["kasiamaria","kasia "],
"l44ggce7ocely3snybuib25q":["kasihakucuan","Aul"],
"otuv4th32fbv724yaiwfcgze":["kalynge","Kasper Lynge"],
"4a6va652zenlrd4ct5f46cjd":["kaspersoeters","Kasper Soeters"],
"ze5r2kclcieoi4s4nvr6y6e7":["kassingout","Kassandra Zahra"],
"xhonw7xlgkwtwt3sggnydein":["kassiekitsune","Philosopher's Stone"],
"cmsghhzhhcyzlahh7i3bafjg":"kasandobosco",
"huw7vppudohvato4t6eb64is":["kasydmk","カマダヨシアキ@META-GLAMOUR"],
"27uyaarkb4lacgenlvgjhoho":["kasio","Kasio"],
"t72wzzkzaputd45kytfnfhrg":["kaseylansdale","Kasey Lansdale "],
"km3xmvfbihrf7n5lxbvhgqhy":["kasodus","Kasodus"],
"y7oqlpedm6korleomvlzwu6y":["kanekaspar","kane kaspar"],
"tnbgudljtnjffra2azqecmzz":"kassed",
"ohlz33mk4zbf2225pcymk7g6":["kashiyuka","cassiane"],
"mx2qnanhmgkxsup4k4pei6i3":"kasimirberger",
"bzkdirxr4i5locpuz73kxfny":"kashifkhan",
"7ypltn2cxvi5gngrsoo63sfs":["kasudbay","Karen Sudbay"],
"cvmykwiwqepxxd3vposa5c3j":["kasaiwolf","Kasai"],
"4gsvorddnwixxmx4halnkh6v":["kashewnuts","kashew_nuts"],
"mrfe6q2gqlxal6gqf6v4p472":["kasper-vm","kasper"],
"efbd77heyfhybhpfahnccnlr":["kasprs","transfagther"],
"jqzrszql5lpq3swhp7igcuxk":["kassandracries","Kass has feels"],
"tn5ucqqws4rrhlv256d5o6k5":["kassymbekova","Botakoz Kassymbekova"],
"5qybin5cmewduroxdzhzsbf7":["kasie","Kasie Hunt"],
"65yyxgeslcuzuasbxkdu4buz":["kassanova","Kassanova"],
"ddjezi7ncwtl774zls67xxwr":"kasperterp",
"txcwce5p24xhshrk4nz5dbcd":"kashaudhan",
"3zvzgcvhub5i7zcn3zgk7xln":["kaslo6064","Kaslo 🏳️‍⚧️ 💛🤍💜🖤"],
"4x6oemcza3xmhxjd5usbojz5":["kasanova","kassy"],
"ilr3u2azs2yn4akv32lvzyg5":["kasophism","kasophism"],
"5ltpfq3f4odokgbofkhllhld":["kasil","Kasil"],
"w3q7by4pjicv5wtsnx2aet7d":["kaseyleblanc","Kasey LeBlanc (he / him) "],
"sbgznfymckdubgrkzv456uz4":["kaseylane","Kaseylane"],
"4l7dvqjjobcxyx3dqv45emhg":["kaseykat","kasey"],
"bx4avfawd7fk3we2tf6l6d2t":["kasseinated","kassie 🔞"],
"vesjktfqrdzrz5snnbvatkdb":["kasumiharuno","はるの かすみ"],
"36ltsngkjxt25cm5dpd373gj":["kaseykyle","Kasey Kyle"],
"zyupdmro4b2tccunufmwklnz":["kasslover","カッシーワが大好き"],
"4wgscztbrh43ds346snpbmgy":["kasairei","Kasai Rei"],
"ff3maqzbviy6hsbjl54z4urk":["kasha","かしゃ"],
"vqzlcgykh5rxhx45cskcdqnd":["kasvar","Kasiyan Varta"],
"sjrrjl44vqvrz2rmtg2ymxto":"kaseyk",
"2idil3u673hvh7gyrfzwnzzy":["kasumi567","Kasumi"],
"e2tijs5vuxijjb2abmpu6zht":["kashcast","KashCast"],
"dmvuydbddr7fh7xwwce2n6wz":["kascha","kascha"],
"q74kbfeoihiohoird3x62mtg":["kasuke","kasuke"],
"pywedjy6dezanecsuciktiho":["kasutera","kasutera"],
"n2epgoowjpveepsmcagwk5vr":["kasaiyukitaka","Kasai（葛西）"],
"zzfekslswije2bfg5znwyrfs":["kaessial","Kassandra Fadeeva"],
"co7ibyob4dnej7azgs3ajwe5":["kasaharu","kasaharu"],
"3n7mpsskz2v2csdjvi25gkbv":"kastman45",
"7bqtrpcxdzgaedwvdzl7c347":["kassiboo","Kassi Rae"],
"uprggqlzgdnf7urfogpc4i77":"kasiapeia",
"4eqhugb26npjdv6aglaxtird":["kaseydotcom","Kasey…"],
"xwakhabkstofwrtvlvsfiwgr":["kashikakes","✨KashiKakes✨"],
"htmurxp3ahae4walgvesra3c":"kasrah",
"rzl7erfi4zzv37jm4gh5kvyy":["kasuhearts","KASU-HEARTS"],
"4y44c3xcfaazkpt2kfmtsork":["kashii49829","Kashii"],
"6c4ec5gurvev6drbuxzhn346":["kassyluci","Kassy"],
"bgpg3jiiu72rsuu6rnt3cgm2":["kassetto","Kas !! ☆🪲💤"],
"22owyk2shizf6azufuaqcpoq":["kasasaginoe","ししゃも"],
"pbfsvuw5flilveptniv2xryn":["kasodanikyouko","kasodani kyouko"],
"cwst2hrwymdnlvhfapzuvabo":["kassxcii","Josh."],
"xebik6mkhvmdvd5bs6z6fwza":["kashimg","かしめぐ"],
"phowjltyocvb42mbg56y63m2":["kashinggiwa","Kemi Ashing-Giwa"],
"nhisw26va5ww5cb26l3mn5xn":["kasad","Kas"],
"4choe2thay5rbv6mrlxzxuek":["kasru","Kass"],
"3h6qfvi4exbxemzkbppbzoje":["kaslana","rein 💧🔶"],
"vaap4yrzlnphxlwicm2s4gc3":["kaseytaylor","Kasey Taylor"],
"hnjtgvxxvji75bsyrqzzdihh":"kaspervld",
"dfphyjfgex5o3z45nef74wmc":["kaspathot","sam"],
"5okddyutx3wjsvynsmeia5vo":["kaceracer","Kasey"],
"73o2r4hxqzw3ofcmm7ntwkd7":["kantiensfw","Kasper 🔞"],
"nbflibih33x4mlizfahi6fat":["kasendrith","Kasendrith"],
"fbom3dzkhqek4itsbe4zx6k6":"kasied",
"4macpw6lsff4cbae2fyah4eo":["kaskas","Kasi"],
"jfj2zi77ijrlrgbbm6uvqhn4":"kaspaar",
"qmnn4ojq4zwaoqqrkzzirisl":["kasatsun","mar"],
"5gqhzihydviq5aeurxoygeg6":["kashti","Kashti"],
"gtwnxaez3y6ojws5m64n52kd":["kasharaylo","Constantine"],
"va4uts5y6oh74ad2xmo252um":["kashikoi.isadragon.fyi","Kashikoi"],
"5kkk6xvxiwlrv3waa2lnllp2":"kasperaky",
"k2joqvvuubqbi33uv4ej735k":["kasumagic","meryl | kasu ✨"],
"4mrnbhr2axx4ttjnk5o6mbpk":["kasdad","Scarlett's Grandpa"],
"oz3qemuknjnnqopstl2ko2kp":["kasper.blue","Kasper Aamodt"],
"hb5wn77vqfz6sfokplzhzarj":["kassinu","Kassinu"],
"n7fgnvzdzhtvvr6gcxeo3b65":"kasayev",
"qzfbdwx37wslzt7l5llykqxc":["kasylwolf","Kasyl"],
"7po7r5zsebq4ivaupbkjerwy":"kastygian",
"gwujapafs2cmqigcakfr7wdo":["kas0uba","ꀘꋬꇙꄲ꒤-ꃳꋬ"],
"gzythbhqll53zbpuqc7qdmbx":["katkass","Kass 🌈✨"],
"oybjs2er5bff236td4542vco":"kaskarino",
"gqwzs2dut3fqdnlgdnb6x7e7":"kaseki",
"nmp7qlpzjdqx6frm7kvy6xrj":["kaswhy","Kaswhy"],
"arkysmt77u6r6726sb4j5asl":["kasech","kasech🍁"],
"6q3phk65svrf7jrwcwynofb6":["kasischmier161","Kasischmier "],
"mypeeyxvvng3xq5ds57r2no5":["kashnitt","KASHNITT"],
"mdvecqcvbld35xhag2wam7zc":["kasemenova","KA SEMENOVA "],
"jil5ao4bfsjwm5gzhafs4jyf":["kass-lockheed","Kass the Boofderg"],
"hig7llsrckocubudh7nsh3xv":"kasgami",
"zqmc4qkdozjphdfql3byavft":"kasandragottlieb6",
"ah4vhmufvmlqweyqxpk6z2w6":["kassiopeia","cassi ✨"],
"zqlu7vlwwdavumgyfvbinwyj":["kasmut","Kasmut"],
"q6ywp2jomews7je64wqtj5b7":["kashihi6","椿"],
"rden7xezjlxfl7mrlebvq6wi":["kassialeaf","시루방"],
"t4ebibns2pwhovu5khmszees":["kaznec","Kass"],
"tw5ffbhc4747j4vwnvwoo6kn":["kasxx","Kas "],
"xfsusanswmui3wneqxmftaja":["kashiin","Kassy"],
"5x6wrdt6mdygudgrthmczaim":["kashmirlow","Kashmir"],
"oedhcpad226zgdrqo5uchfwk":["kasuminasai","Kaz"],
"rg5tcnwawl44gohesibwciay":["kasaiyamada","Kasai Yamada"],
"j3n6lhuuiadfrstiy3farvqq":["kaspianhallow","Kas"],
"6cysc6zlal6gyphbyv22ragi":"kasperlaursen",
"qhqttz763rkovyzp4oim34k4":"kasaiyoung",
"j7rp34ylcvtcn4t24sgpo2sz":["kassiekeegan","Kassie Keegan"],
"mvgumyze77adpzw74ry2rg53":["kashatryah","Kashatryah"],
"yhsd54cz7gnek2rv7fklfaim":["kasoubanohai","ミシン台"],
"3su7x2tjwalwamvqkf53yu2q":"kashup",
"qtbxf5ltbwehrocuca4qfy24":["kasparletheater","kaspar felix"],
"fdpfvpnrrtvymvsce4sdywm2":"kasparelis",
"cvt2q2aepprbnlxkxezr6i5x":["kasuncfdo","Kasun Chanuka Fernando"],
"uzsuhmt4t6xsstxpj5jwvpb5":["kass-sassafrass","Kass Sassafrass"],
"3jjfalk637sticlohm4muurt":["kastatic","Jenn / ジェン 🥦🐑"],
"yetonfa6dswkyqo2v2dansoi":["kasiabrenna","Kasia"],
"3jxkafpgc7eizaez6tpugrk7":"kasanoff",
"n2zmkaws5uxtoys4ifr5nwpl":"kastru",
"hun76yyertrzwhghcqbnxrph":["kasujja","Alan Kasujja"],
"bxpovvp5bludepl2iwnciin6":["kasaleiro","Kasaleiro"],
"yhvgqeujfksshhaxdicdcboa":"kasperr",
"6oqp5diinufzclgq4itc62ay":["kasahimawari","Kasa Himawari "],
"thfzxd364txfym6xdjw446hj":["kasp","Kas"],
"xa4cakphe4drixxzefgfplrb":["kaseytransgender","Kara girl :>"],
"rzr7nkxvw5nv7ttqiqqqhoxl":["kassieabouttroja","Clara"],
"yskqz2lntvkziyqu2b472qeg":["kassh","Kass"],
"dplc7onbspqlqg3mej7ihdlt":"kashdav",
"m4664rmzqr2i5ynqefjrx7wm":"kasafc",
"73lrctvf6honk45zele55umu":"kasondra",
"5onrl3dhxhf3f773j5xx2hlu":["kasayan","kasayan"],
"yby4xbgkgpyfwq3q33pjjba6":["kasumio","カスミ"],
"szmpsaqbbu7wysrkx3z7guwt":["kassyoshea","Kassy"],
"gvddc2oorvwm4g5gwfxbykwi":["kashewkiddo","Kiddo :3"],
"3xzak2jh2z4kkq4zbv3xbaow":["kashavarnishke","Dear Rat Girl"],
"pcctqnpiohtsctdoeeifxnya":["kasimkoc","Kasım"],
"e6humnm6jjt2vi4ferfy6odn":["kasparknusper","John Elton"],
"bl6rydppri2jwoy4s6aiuxgm":"kaserious",
"g3dx2s32aqrldxs424tjwta4":["kasota","Devin Glaser"],
"i5c3xdnd7vgm7tyevrt44lgu":["kasienka","Kaśienka"],
"tqdu626la4zn3gqi2pd4yq23":["kassiewright","Kassie Wright "],
"7fx2eqwwsrw35arsnrd4joas":["kasiaturajczyk","Kasia Turajczyk "],
"civlil3gru22kqehlhmqu6uo":["kasperwerther","Kasper Werther"],
"mmve3hhdv47245mhmsrycyfi":["kashidingspot","TheKasKas"],
"6b6a456rvldxvbrwkk5m2uxb":["kashymcgeek","luiza"],
"wcuya6licqeykabavdnplplk":"kasaj",
"4kdw2bztxuufwa5upyg4d6ms":"kasibu",
"ixyp7jfzcgecjpbwqpm2obxq":["kasandra","Kassandra (ka_sandra)"],
"tqm2eudb62wcj4njwrvqajzc":"kashuno",
"qziiusixoiqupm6cy643pj4i":"kashinkashout",
"mez5hmv4bp5ipgp7t6rlq3wp":["kasmeen","Kas"],
"ia5jh2nxy5oh6cwwyvq7m6in":["kasyl","KaSyl"],
"w4valayu7lqilgglau4wdkce":["kastney","Kastney "],
"bm4ow456ritgloppxdsz36sk":["kashinoga","Kashinoga"],
"e523nk6ns7us4ojcqg3lwqmw":["kassb","Kass"],
"x3muzejnnifjsklbf4ifdc52":"kaspu3",
"5ksmt74l66vmqunznqbaxjzp":["kaseikiwi","kiwi"],
"dfkz3uhkwsdaqhxddnswboml":"kasufrog",
"3bo4fxrv2xg7lfossgocpj2q":["kashix","ª"],
"nwe622gcxdc5hgnka6ddoxhy":["kasxo.art","kaŝo"],
"g2vhqbqqrozvjxih5duqu7ks":["kassatto","KASSATTO💽"],
"cxd6kng7cdjk7haacsiaynfy":["kasumii","Kasumi"],
"xfpfgozxudzk6einjdnozi47":["kassandrag","Kassandra Gaffney"],
"n3fhaxgzc67ej2nyabzlopqv":["kassio","𝕶𝖆𝖘𝖘𝖎𝖔 🗡️"],
"jekegrutp257kdssgeeujipz":["kasasagi","凹凸のあるカササギ"],
"kw23ij5v2jkf3vj2aoymm22h":["kassandravalentine","Gwen🏳️‍⚧️"],
"etsf5jpzxneee5xi7hiewnkx":"kastomizovan",
"75nh2rzn4zgqgtx7qtvefj4q":["kasaica","hi im kas"],
"7bdfxvaqcfvriiol3xjb7ypl":["kassdog108","Rob"],
"ig7jjgueypw4rwok3b2fyaib":["kasathedog","KasaTheDog"],
"sedl6mhohxhkbttnt5ucaw7z":["kasemoch","Kasemoch"],
"ezjwkkabknwttbdapqo4guvs":["kassanova42","Kass"],
"5e74r62dajhjfto4oy3qfmwo":"kasumijustine",
"vnhta4s2giqlnds76u6qhdcy":"kastmi",
"bg6e7jr5alvhfytwldoi2wyo":["kasra1364","Kasra"],
"kpgpupdgfld6qrvs5ifsuh62":["kasumiwotaberu","かすみをたべる"],
"6l4i223n5vck7nznzeeih4kh":["kashimaadsen","Kashi"],
"4dalcvjwsnwwe5pryvztiuh3":["kassthedragon","Kass The Dragon"],
"eokmt2cxzdfhm3zdfu4z6orv":"kasperj",
"hvzbmrtuuoxqg2ydd6i3mhzq":["kashif-h","Kashif"],
"6ue6gbhbj5olmzqay5t6u5fc":"kaska",
"sbpsi4vbb7eorf5274pibxuc":"kasupassthrough",
"ovzhkwu7h63qys43pf7sgemw":"kaswad",
"ftxefs6ht4nutaofkf6ua4md":["kasano","Kakeru Asano"],
"j5sn7uujy2qhwcnjysdhot3r":["kasugatomato","春日トマト"],
"m5pdnt3oog3pmo67ipjadgj6":["kasparhen","KasparHen"],
"jcu7d372q3ey2a6qj4jk6wbd":["kasai67","KassFox"],
"rtltpllyaq5vwlfskovpmxsb":"kasoban",
"tr3lyowv5juqddbecskr7gch":["kasimyth","Kasi Myth"],
"p5fjkeh4e7wgee77lsga6l56":["kaszronda","Kaszronda Dawnsinger"],
"xehr3w5knxhkuyovk7syie7i":["kasamuse","Kasamuse "],
"t6jkxuyh3wxkcrwxc6xqp622":["kashnight","Alex"],
"ptwcsk2rhsijqqixe52ewsc4":["kasgen","REAL skeleton"],
"psehqk5633vubre3ohlvicqm":["kaskabeltz","Sai "],
"xphy7tjrzmvacuxzxp3br5df":"kaseoh",
"wsoowzc3idysrkudp3shht3h":"kasa",
"5v5y4pur36alsxyuzdfi233k":"kaseylaurynn",
"shsvv5l75rkfiezbyymj5azs":["kashuu","kashuu"],
"jrkv2djywxvn6giq2tt6izda":"kasmom",
"uo5hze5sfjcfjdq7apvqph4r":["kaseinitrat","Onyu"],
"rb5tv2rtvup64ardqwlfyjui":["kashi8s88","カシ"],
"fd7xarjj37v5axbxczpgqj5c":["kasparsd","Kaspars"],
"5rh52bh7ka6vp6zebgvrtouj":["kashuan","kashuan"],
"b2cwtrcxzbjyhawkoxvybemy":["kasenyuu","荊木幽々"],
"vw7hs5mc26suxb7mmr2pdixi":["kasialin","Lin"],
"x62jsdzuigkt7nbbz5p3vi7d":"kasinkain",
"qwzxurfnhq7vmsbzcfdtxubr":["kasap","norihoka"],
"7fpl7xotzob2akexdcisoxus":["kastmihama","K.K."],
"7diesjpk2rdx7pokreosgnzo":["kaslansefat","Koorosh Aslansefat"],
"gejzilvkn64euwl2wilotqzk":["kashbunny88","Naya Kash"],
"vmkqq3n2yegdycjtcav46y3q":"kashinya",
"pzarqh3ybjlxiygfesytacjl":["kassiopeiaandor","Kass ❤️‍🔥🗡️"],
"z2msgtrgupu5ipcvk5pdidkz":["kastanie","Kastanie 🍁"],
"6ykwmw6ns4irbc66wu2bmv3h":"kaseym",
"zvdafk3464h22jsusr7ucwaw":["kastanjefox","Kastanje"],
"22otjqkxi7efluju2zjuxzkh":["kassykalico","Kassy 🔜 FursonaCon"],
"v2cdo6a7rqxdjom63ypoquse":["kashuza","kashuza"],
"eh2udq5igfid3vm5eim3tbnw":"kastamonu",
"pivnzeckncl62cadm7oz2etb":["kasakitanari","Kasaki Tanari"],
"ntxlyfw3y5z4rsrxalh3mh7y":["kasianie","Kasia Nie"],
"4ypdkcxbvzvifjjmsze52wbt":["kastilo.nuak.org","Reĝino Kastilo"],
"i64qf6uc3taqkifdinv372vq":["kaslis15","kaslis15"],
"b2p4sqb3454yrml77bqxdlnh":"kassdee",
"mfz4gocyn54pyklsqsfy66za":["kassiwan","kassiwan"],
"suwvjphxajp7sstoq2l5biep":"kasya2901",
"5mdz2avt4uurwfnhyluj6zfz":["kasiaslupecka","Kasia Slupecka"],
"r7yca4shoszpdis7xyld6si5":"kashnaladak",
"s72sa6pdfdd3lf4yxj37w5lv":["kashish","kashish"],
"6kngtb6cnikny4yqqxbjxkjj":"kaseman",
"md3aha6kgfh4kuqqg5vl7qld":["kasscoleman","kass coleman"],
"o5hjbsfee3rp2xb2ltwtdiel":"kass1e2",
"unp6msyxnvuwpyoboryk55e7":["kashmeread","Kashmere"],
"6lxodgp7w254xw7j3raxtscr":["kashdamoney","Kashdamoney"],
"5eqylk5ywclplcbcipsv6f7z":"kasslim",
"vtfuzcrgxbfx2xbyjgmwncxv":["kaskete","Kaskete"],
"av44yd6dt6l2l4rl3f6qobf6":"kasharin2",
"5ctm6jxxzo3kv2vi5zdzkpzg":["kassettenkind","Kassettchen"],
"jt3wuye2tlztssrlj4g6mr54":["kassiesmash","Kassandra Nova"],
"umg5bfkuzo3y5d6gvh6xsmmj":["kashiwa","かしわ"],
"44ewea2iwvbbk33hxcqgefdo":["kasieczka","Gregor Kasieczka"],
"jvn2drnglylpob5gbe4gx2t6":"kastanenka",
"gi6rls3nkvantynrltn5yq27":"kashiart",
"vvz64qlhawohuqbxob7z3hz7":["kassi0peia","mary"],
"elbd7umlzm5qolkfmjmbk3gy":["kastella","Kayliegh 💖"],
"rdnxfcmgu5z5piebaslf46ko":["kassithefoxxi","KassiTheFoxxi<3"],
"42obvul33fklfwph74u2h2zz":"kashapatel",
"rjat4i3bcfrvtb6rmerftm3x":["kaschiyski","Kaschiyski "],
"zrqqag45boyinejzwelalcuf":"kaspark",
"5rtisz44jd2yswhtgaotnjkf":["kashani118","اِهم"],
"xgb7pwxozsnvpieji7zamj3z":"kashiph6",
"h4otccahiyonzlfdcnrwlehk":["kathykastner","Kathy Kastner"],
"x323jwvhrcbxdk6cj3euvucr":["kassruffi","KassRuffi"],
"x5iya6rmnxov6wwgsow7laqv":["kastroinky","Kastro🩸"],
"jdd7gnvm7eqxzg2ycl6cpvbw":["kashiir","Kashiir "],
"tg7wpz5ditccoilnfq3wi7b5":["kasakir","Kasakir_Mixtly"],
"xnozkpeizopiwrjgp6wx45mi":["kasnudl","gabriel 🍄🌿"],
"lx4lm3mezhteiotsnr7y4m6h":"kasperh",
"7tfyrxfishszcw3x7xusnzpl":"kass0",
"uinu665nbsr57erj25wc4okc":["kassyarf","KassyARF"],
"63l7klmrt7unzonpyjf52xhx":["kasatron","KasatronArt"],
"udgjwxm6iota74gwkplpxmlu":["kasja","Kasja Weenink "],
"wd63bxl3oqm5ciuzjpmhui44":"kasperlcurtis",
"yrmtbljp67uae74oxqiolccw":["kaspian","Kaspian"],
"jfikyur5n3zjbfu6eykvas3u":["kasion","Kasion"],
"eqsigaozbo56i6nqhjkzipo6":"kastilloi",
"73ibpeaclbudhuqmtm7htyxv":["kasha1441","카샤"],
"7a3v7q6xbw3cy4wqmqdvxqa5":"kaster",
"jgjkj3c7y4k2fcmkupf7fxfz":["kasaizor","🔥𝙺𝚊𝚜𝚊𝚒 𝙺𝚘𝚛𝚒❄️"],
"goh4fbx3hxttputvecckpszy":["kaserlin","Kathrin Goldsworthy"],
"an32vjjzsddtnjh4ipvitnpb":["kasuak","kasuak"],
"c2dqjjkb3kyr42jxjpuosz7e":["kasestory","카세"],
"k5c6ducgr7mrbm5zzgyfnlvg":["kasparexe","Kas"],
"vbmppsnc4slvkf4rez4kcuv3":["kasmkave","Cowboy Bebop at his Computer"],
"mtibpn7q6d7d2oe5dwwzlwik":"kaslo25",
"rull2qfrqcz2l2zdm47tjrbh":["kaspi","Kaspi"],
"bqqmncz64jb6sjggaxdryt6h":["kastanienfraeulein","L."],
"gfctg2jhbueugpcdafb2ud2t":["kashievans","tyler"],
"6emcqpligexozbxr4ucavvxw":["kashima-bs","佳嶋"],
"2nvgt3tx4x76g2phqqeoodqz":"kashima108",
"5x2bm35ju5xmyizhykbkdsdn":"kasaharamay",
"g7xmjfnfdjz2py5oou5q3b2p":["kassin","Kassin "],
"tcmuj6vgntkamp52b52r3hor":"kaseydeagamez",
"hkjtsvxpn2yjqfxingjqrhlz":["kasutajubaka","Katie"],
"zqfrd2gcfp6iumgzl6niy5uw":"kastman4522",
"zvk2pl43ujikvc62crqxiq3x":"kasen",
"3earpresc2xudo4ic57xf4hh":"kasisma",
"yxe7biitbj7bqhmumppqad74":"kassan",
"5ghmtejpkdrxfad4lafzrnq7":["kassandrameda","Kassandrameda"],
"2ymbjwg5sve7nky3b2k7azq5":["kaseistingray","魟"],
"aksebvcv5ahtboodut64zyon":["kastoluza","Kastoluza"],
"keckif6vgrh34oqs75ybj6ov":["kastronome","kastronome"],
"o5qzanpxxrwywv526jfjxgqe":["kasoka","かそか"],
"f5h4kaaatcli67lcx6xirf5m":["kasasagi0803","岩城"],
"nntgc2dodctjtnga3vqhegvq":["kassor","Kassor"],
"3c5i636pkmlunnvjtrqoopwt":["kasutera00umaina","蓮"],
"bqvudz5vgkc6de2suqsomgid":["kasako","かさこ"],
"cm3ih6zk653wzmyybumrbbxd":"kash2112",
"b76mlpnjj77lizgzyjpzifa5":["kasenn03","S.くさか"],
"ohw6p3xem6nunsuijiwuyh5q":"kastman4524",
"eabnx7skbmsfvyna37uh2c7z":["kasaundra","Jelani 🧕🏼"],
"yf6uo7ankpc4tjrq4j77t6sj":["kasmyne","Kasmyne"],
"gsitqyhdq4mnfrobmjmsz3to":"kastanienmensch",
"fxlzcclnzi37kzwdwjuzbyy3":["kashiyaaan","カシヤ"],
"t5sz2jzfbeeqwivg76ckskxn":["kastacholamine","Kate Stafford"],
"n32xum3ed6aj5lwipeoifwms":["kaseybuckles","Kasey Buckles"],
"z4tpzhcnuepxhxhuh6gjkqjy":"kassky",
"xssaxd4bpzelsjfgm3cjun5v":["kasianchuk","Andrii"],
"szkpnrg2g7dkdtlgurilnblr":["kasasaginohashi","本田薫子"],
"chzkk2lmeu4rxl6wmct23ag3":"kasomi",
"cf3sho64fxw6q3ugukcclmze":["kastella31","Kathi"],
"b7hnpz67lywv4rrnxhf3jf42":"kashura",
"azefk6iqjfqtjqtpiza6uc2o":["kashiiera","Kiera"],
"esgy4uvfpphhk4gotxsxpbxl":"kasuga",
"t3qtogdj7dku7a77s4isz6k5":["kassaurora","Kass"],
"fw5mejj7yh6nlqtob6mcuzp3":["kasemier","Kasemier"],
"4riqrxrqusxi6y2imgdblpj2":"kashia07",
"6nrjnawxzzogpfttugbstvv2":["kashi0kaxeon","Kashi the huskergal "],
"fsu23qk237qmr62nvc3jbp5f":["kasai2002","Kasai2002"],
"zylhhaldf5pwj7fx2bede3t7":["kaspyn","Kaspyn"],
"soqgqw3qj3xmzqlh4vpdiuiq":["kasual","Kasual"],
"c2s5vxb65qz4s7csumqrxx7t":["kasper1523","ɹǝdsɐʞ"],
"wxrtswd4xbl3ukvmcpqxwnj7":["kaschmi","Karin Schmitt "],
"y74vb4hgum5snqshneomiwbc":"kasperz",
"7m53d7xwvblyjladzooqcbux":["kasadilla","urs truly "],
"x6j2q6lvat27ehd5k3ywn5xj":"kasumingo",
"s6phpe6adz6t6vcufmbnqprz":["kashiwa-asd","柏市自閉症協会広報"],
"32riaduzxyxijgvw4v63d6y7":["kastel","Kaz"],
"kwbcq4spjxhr3go3uhxgietu":["kasbaka","kasbaka"],
"mwvn3k7uh6jhuhoet45gakut":["kastrel","Kat Steiner"],
"q5haj3kkoydpe22mxf4j3dhd":["kashicola","Kashipan"],
"wucxcta552n2i2hc7jzkvyvn":["kasovan","Kasovan"],
"rh5pufknvpqflqi2r63bgqqt":["kaschberl","Kaschberl"],
"i3om72lryjnufgkxgwz2psf6":["kasane753","カサネ"],
"y4ktvljcoovo77bhvm73olnz":"kaspar19",
"2u6dzf3okear4i7e55qffg5y":"kaschi",
"z546nyjneeqmb5rymdiag4oo":["kashimon","Kashi"],
"tcdeqnrodpzjordixrfdrkos":["kashinorei","David Cabeza"],
"wwlpxzmdwhqxt2izvy4dw74z":["kasumirk","Kasumi_Rk"],
"ebpjp6brktq4hewnlxot6qcp":["kashmo","Jin"],
"z5b67qocwoofipsh2w46n4j7":["kasayler","Kent Sayler"],
"6f4l2lgt2u7olyjzfxm6wy65":["kassandra74","Katharina Nickoleit "],
"neafxyubdpasgyqfoyuev6wl":["kasai2f","カサイ🍺"],
"wsrkuipvpoj5ae2uqbgp4pj5":["kashi8s99","カシ@創作用"],
"23w4so4pdtcshnncnaixle63":["kashika","カシカ"],
"5eoy4wxqabhgp4t3f6r7mjtz":["kassmonday","Kass Monday Cosplay Porn"],
"ytbxzf4hslbpcpp4dp7akqat":["kasimirdederichs","Kasimir Dederichs"],
"crxthbuedygrzlecjzk6drn5":["kasimirkasulke","Kasimir Kasulke"],
"ywo2534w5k5cxg6s6kns272i":"kasasagidesigns",
"y7bpeozvsdlglr2u34c4aoav":["kasimon","Karsten Heymann "],
"34evw5o4en6a2regvvw4xnwj":["kasulja","Ksj"],
"iawbr6yievtaeww6w57or7am":["kaselakh","manic pixie dream demon"],
"53rhwqo6cqg63b5zbh3p2thz":"kasualt",
"7clfhcd2j5tozj3fkgszemfi":["kaseyryoen","Kasey Jueds"],
"cog57abzbe2yydfq7vv5hkcw":["kashiro","Kash"],
"5ybj7bvzf5zv5qpsf7xcycyk":["kasurequiem","Kasu"],
"wevufxmbr575ivbycn5xfu6y":["kasscinn","KassCinn"],
"zakegvo65fd4vpu5w6srtacw":"kastman458",
"ypz3p4lu6dlogoxpq3wgo2ju":["kassidy","Kassidy"],
"a3oatqueirrvaxsbmcug2f4h":["kasratabrizi","شاعر و ترانه‌سرا؛ شاگرد دانشگاه مارکسیسم-لنینیسم"],
"vquhe3lu3xs56gimybkezeqe":"kassandra2191",
"3j7fm3zz2zdb7ghvdn6k5gxs":["kasem23","Casey"],
"urpucsy47hrjtrsdo5vn3cq6":["kasaimo","Kas"],
"oiu5hyue7z727tnxgntp5xjh":["kashiak","Kasia 🤯"],
"uy2k6svnrreei5fvuj32n2nf":["kassandra3","KassandraB"],
"kdbw5jfbwooa7yq3hxchif37":"kasamangcerena",
"nuctgc6uq4glauo4itad43w5":["kaseysnep","Kaasey_xvx"],
"vkut44uthqzzkusmeskcudif":"kasun",
"vqx5bxftdj7u7fvozj6leohn":["kasparkarssen","Kaspar Karssen "],
"64gvi7bvlq2uznalp3bpuxyw":["kaspii","Kaspii"],
"pkcd7ksv5snefl6pmttqkubd":["karolykassjr","Károly Kass"],
"475j6eohrtmoy7budcqrv26r":["kaschmirko","Mirko"],
"ku5szf3p77qfey7c7c4bbjw3":["kasparrosager","Kaspar Rosager Ludvigsen"],
"phmoam7o5y7yublambyc25vq":["kasandryx","Kasandryx"],
"p66en3qgibg6zomhlhi7r727":["kasamiru","kasamiru"],
"6xxhfqnrkp7r2qffcpe4bg4n":"kasandreasereno",
"y6pqugynqnpnywj2bkcjgvui":["kashiandonna","Donna Kashian"],
"wxh45eighxlv6io3nwjcgwht":["kasairubystudios","Akuma Schwarz"],
"yc5m6p5fkj2ceesgwqfu77za":["kasiakrzyzan","Kasia Krzyżanowska "],
"uqsawovmdztkwbtawqef5as4":"kasjopeia78",
"qg4vpirnlmvcdwf6emcfqlcd":["kastheri","ХКБМ Андрійович "],
"7uirmhnexbhgpebn2zjh2dkw":["kasimirp.magdamir.de","The Walking Dad"],
"5auwt236567piodfd34yzn5w":["kasssidy","kassidy"],
"6csa2t2jsrvbu7bpvl4vgtc2":["kasimirheldmann","Kasimir Heldmann"],
"s6vou5zhbi5iijtg2hlfcjbv":["kasukabesadou","春日部高校茶道部"],
"mkwwcmw7jduoze6g2a5y2dd3":["kasparmitk","Kaspar_k"],
"55ujksogselvgfpcwexvkiwg":["kasou","花想"],
"peaj7nckqh57sko6m3qezsld":["kasogokiburi","Pasukaru パスカル"],
"ljsv2pf3pn37o2yg7bn2wcjp":["kasina","Nastassya"],
"rgtipmbgbc5fsv6qao5nalme":["kasimir","Maximilian Kasimir"],
"q3ux5xb3z2qoj2anw7icxxwh":["kaspernatze","Kaspernatze"],
"ycbmqcpvg65ihcjqgucak7o3":"kasiopea",
"b7fd4tkllqbrtmw2a7u5lxlx":["kasheppcpa","KaioKen"],
"7snyctjnebptw3qig5yzrltr":["kassioppia","KassioppiaVA"],
"ptx4whcq6mjrrqxjpjdgztt7":"kasparow",
"val7xryrlhhxjq4soksg3i66":["kasiapaprocki","Kasia Paprocki"],
"svs47mje2ea7ws2tnn63lycr":["kasco","Kasco"],
"hsqevyqooi3qsf64yzm3ewzw":["kaspervangelderen","Kasper van Gelderen "],
"4qhzkhmxjtfunfrkputflemr":["kasilyn","Kasilyn"],
"cvex4mjtdh5m6zd6h4gjzgvt":["kaspar0815","Ratatöskr"],
"etw4tc6zps7tjorqda7kghrv":["kasami","Kasami"],
"mhe6evlxg6t7wfrbpzjelkmy":["kasirith","Ophi"],
"zwg3icyrxxr6jocpmruaqlqx":["kaskin","Kaskin"],
"dmgfw6zggeta6yxfri3cheuz":"kastamarov",
"klyvegmxcgiuejeqbegxa2vi":"kasyopa",
"bq4335l343poobehacor7w3t":["kas007","Kamlesh Sawadekar"],
"t622xnvkgkpep2gpeqz5csgs":["kaskel-kiezblock","Kaskel-Kiezblock"],
"tjyrqztm4cjdckry6677tphb":"kasablanca",
"kzprwgu6oyiaedfdpxuuiruv":"kaspyy",
"wp5gbkspmzwkxed3e6u6bkxh":["kaijukasey","Kaiju Kasey"],
"qx254irbkl3eoiqrtpcgh6yp":["kasarian","nate / kas (he/him)"],
"4edp7dksd4vyzsrvm2bvcr5v":["kasetsuyosuji","Kasetsu Yosuji"],
"awmnlo4uxgrjx25tuyqw5g42":["kascady","J.F. Kascady "],
"nlmfc2vfjmyjgv7uzcd7itry":["kaskraaker","Kas Kraaker"],
"3ombhxnm36wd5ub2uhkb354y":["kasaidraws","KasaiDraws"],
"6z7lh2lr535yok4etusmnmy5":"kasheka",
"tvdnnpw4iik2rvz3rcieonhr":["kasseusmaximus","Kasseus Maximus"],
"7i3qgr5usfh5hw2vp4gaoore":["kasraferdowsi","Kasra"],
"efzjn7xnb2l7r4gahemx7qzi":["kastanjez","Tam"],
"56jtth5u4ovh4rgtrnaxf4r7":"kaspu8",
"snhpjqcd5do6sfeqsakzu5ni":["kastleseeker","Kastle"],
"iknopedahfhhg6eyhw66jmq4":["kashemir","Володимир "],
"hvukv6jqnunyv22cbhbuyq4u":["kasaharamomona","✧²"],
"zviofw2tjzrhy372jbrraqcw":"kassiopeia23",
"fcckyydjmmxzj5pdla5bc3ce":["kasuga-kun","Kasuga Kyosuke"],
"4zzlqbc3ugxvow6emvlreryx":["kasimir21","Doris"],
"kdaihwsoqpumdwcdf2b3snhm":"kasuminn",
"yctx4uyg7h6725wqg5ajrxge":"kassaryln",
"hforrfs43ijjymvgvstebrwh":["kassis","kassis"],
"ogmjc2fv6zzuv2tp3ib65hwy":["kasmanaft","пшшщт"],
"4i44n4dqhhbhiwkseh4fqcji":["kasstrick","Kasstrick "],
"6wrczwa7lvomhc3hhj2zqek5":["kaslanaalbarn","Kaslana Albarn"],
"dhwfkcaxqv7dd7pqtdfa7m5x":["kassettenbox","kassettenbox 📼🎧🎙️"],
"3ksmssred3f6rzslqs55dak7":["kashiwamochi","かしわもち"],
"mxi3qi3jvjjg7xte7zxeu3vg":["kastencarsten1","Carsten"],
"lxidpjkkqyuwtzjucwkn2b3k":["kastafior","claire marie"],
"ij5g3e4mfy3gya4nbck5ppqv":["kashmirstirling","Kashmir Stirling"],
"isazgyq7wl6eggqzvxrobwko":"kasharin5",
"dkaqmsfr46airmdhn4p7wv6j":["kasaimoyasu","Kasai "],
"m7lgp7347zk4fhjpkicvjcnj":"kasa33",
"aznzsphcrvi4e6rbolmnfpey":["kasriel","Kas"],
"tfqwhv4hg4dmjpqwq2fdther":"kassiopaia",
"37u2pzowa3zvqzw4glshf5ti":["kasonix","Oleksandr | Kas"],
"juenpqb5blrlbveekobrtacw":"kashiph21",
"kgv53ibnpogjky5du3bqbhn2":["kashiwa2533","kashiwa"],
"dxiddk4725zvmvnbmroovajh":"kasiaa",
"ly6tue56eyxlqxgpohqhb6kj":["kasialhea","Kasia Lhea"],
"k6hxfdakt3guvz644k4cbzyn":"kashmoney",
"b7uucbzbj3gz6pgph5nlxqfy":["kaseysniffs","Kc"],
"kak7hozkgcc7slgilbm54kfr":"kasey3974",
"3g45d3lprijq2nuq7fulg3ac":["kassiadesign","Kassia Borycki"],
"nbhksbpjr6g6j5zpqfqiezxv":"kastman4510",
"skziyntrvu7ou3p7lildzg2f":["kasper0214","Kasper"],
"a2rtlv46ts55kxkicc3bjf4b":["kassiedee","Kassie Dee"],
"jtcuxaznxotphrs4yadujgsx":["kasstheyeen","Kassander"],
"tsartk7bfs7goxwka2dc6wkv":["kasperd","Ka'Sperd"],
"vr7m2mqa3aigmeicy2ffa6k5":["kassadinvt","Kassadin🖤🌌"],
"25ehx35je256p6dpecvrikmp":["kassel","Kasselpup"],
"ghrxfoifqwvpeegqgnjzovif":"kashydoge",
"7hjy4hcldl5f7rkp7r44dab2":["kazzle","Kas Jansma"],
"w5tosfkddcabimrejq7ueuii":["kaspir","Олександр Власенко, Одеса-Мама, Україна "],
"tqrmfatbk243iyhi4c5tlpjk":["kashifpasta","Kashif Pasta"],
"5msxehtizpt7l3r6yutcmvkb":["kasiiam","Katie(Kasia.M)"],
"iv3mdo3kdhrl33525vdpcfvh":"kasacchi",
"uibxkdytzme4qvjymoin6e5y":"kassandra72sl",
"x7yotlvrttqrulvweepjj4nu":["kastel-labs","KASTEL Security Research Labs"],
"om4yn5aapimlidu7jovsjhk4":["kaseeblu","KeLvin Giante 🌙"],
"o6ex3gcaq66wtyook3udslbo":["kasrarafi","Kasra Rafi"],
"lyimrzwjruikmmo6vs2pi6c4":["kassdy","kass"],
"xzkvgj44ifm44afc44cd7ltg":["kasualkubo","KasualKubo"],
"moihlbsgy5csu5spw3ydvd57":["kasvet","💎 Kasvet 💎"],
"an4fifvfvnbza2ao47d6a2wi":"kastalija",
"phugnudagwlmvzizhmy3bhbv":["kassanovaad","Kassanova uwu"],
"ysiogatq2o7hqa4shkqq2abn":"kasana",
"tlczg2xkrq55ioqosai2rvxz":["kashima24","Kashima"],
"dzpcq6gxrjtxk7ql2zxdry37":["kaskae","Kaskae "],
"vpx3qcsd7c3zqllvkufkqaan":["kasology","kas"],
"jgj4nhfb7spvqqige2w7yp4a":["kasi0rat","cel🏳️‍⚧️"],
"zvwi2c6m5cocb6orwvtm77kz":"kasiniare",
"clbupxwaujwxlqs4jjebmav2":"kasin",
"bmot25p3kdx7pvcxfdlfrahp":["kasperad","KasperAD"],
"3f4hunixlsoizpzernee7cge":["kassemtahersaleh","Kassem Taher Saleh"],
"djtk3ncr364chzzrftorzwa2":["kasnothere","Kay"],
"mqwzk5vexmnlur2zhgfr76o3":["kashikakito","Nina || 🧡"],
"25a47szvq2s2ypmzwbbm64kj":["kasumiumi","Kasumi"],
"leyz577kgiem2jk7pt3n7ujn":["kasnoca","Kathleen Stone"],
"kcl4azjtlcfcc5qq5ajibbwh":["kasimo","kasimo"],
"cpuenxtnfnwdq3k77itulsis":["kasinans","Kasinan Suthiwanich"],
"hikolp7aho32jj7pxykoztwj":"kasma",
"lqhdp4ym2gxhlvtsbg45jx64":"kaspina",
"gwinivkrcdk275acjjizjn6u":["kassmaster","Trinket "],
"khdomgpolyrdxy2qocg3r2fg":["kast11","kast"],
"77be64s4c2ggjavhuqqh6gt6":["kashakay","Cassie"],
"zhaesm7gybqvbkvtbesvusac":"kasperhounds",
"mtgr2g2x44d55gb47nmhocaz":["kaoskaspar","Kaspar"],
"ulxh6kfirchjubrnng7hzo5i":["kaspakram","Kaspa"],
"tzfgsestfm426wazh3536hs2":["kasigoal","kasigoal"],
"t43tcqgxjruc3zoeodq5otbg":["kaspar123","kaspar123"],
"6rdmygspjszlpccmowljefmp":"kassizzle",
"ch3mlsklhwuq7xku4way24hp":["kasl-librarians","KASL_Librarians"],
"ybxax5zg4fy6pbe35lwrmkja":["kashikat0","Kashi 🌟"],
"xz4lu4zz725fr64gehkssxk4":"kaschwatka",
"tmnum2a6fvr4k6j6jvwtresz":["kasumsi","KaSumsi"],
"qlwnr5qp7a33yjc7ycao2uwk":"kassoul",
"xu3eplt2z3c4dv2kowymz6n2":["kaspthehedgehog","Kasp"],
"77kyrzroi2mwujs6ovdislm5":"kastanova",
"j6hudq3ybd5upfyudqudlrvo":"kasp0r",
"xoygbfvwsqk6jxkgez5fqq3h":["kasirec","Kasi Recordi"],
"xpe5wtx4xu5o3hv3pxz2cfsp":"kasprio",
"d6wtextmdf4jzr4oouyapzmm":["kason0420","Kason"],
"wustl43brnpmenzbm5ncuig2":["kastelosol","KAST 💥 CRYPTID FIEND "],
"44nkaiaiipuzymtkxcjfy7b3":["kaseikira","Kaseikira"],
"5dezconzmtq3j7cpnkg4kzif":["kasi-e","Kasimir "],
"ycoct5rmih6zow6eiu2ufdup":["kashibaii","Kashii"],
"dy2xsjarlhyfjc2y7a4qyt7w":"kashidragon",
"ncawv7gy53qwxxcguuudzh5n":"kaszas",
"lj6zx7ud4exwfd6xaugc2ndo":["kasoku","Kasoku"],
"otifjhc7pobtr3j7vyhqyfd4":["kaseymc26","Kasey"],
"xs4giq5k56ximhjd5xnhnlcc":"kaseface",
"qynv5xia5khlmghfw43zsune":["kason","Kason"],
"pdqm7zlwqrvb3kpsb6d6xmf3":["kaseythewitch","KaseyTheWitch"],
"d75tgzryvbpolhwva4ilyubk":["kasanoba","김다빈"],
"vwqksxncjnqnkz7chfsjhde4":"kasparnewby",
"qipl4d74jeng3su4z4qsur2s":["kasaioni","Kasaioni"],
"6x76qjjcjvh4f22wzgzqbts2":["kashirosan","Kashiro San"],
"6enwfwfaxvjkkwvxmfa3mzyr":["kashu424","초남"],
"2jgkb53w3jwez27yxlcnsil6":"kasti",
"6tnkcrigbyjmwp5fiv4ufh7o":["kaskeroso","Riojano loco"],
"vkxa53aeazymeccovdimnxod":["kassiekalicoco","Kassie ┊ Vtuber"],
"kniyq5x7axfbi2pqzt73eqfw":["kas04","K"],
"d6chem27j3jyjtjg4oogqi5g":["kasualkatastrophic","Kasu"],
"b6xhpvzyupblx7uvudefb4dj":"kasladia",
"5dpka7lt4lqkdec3n6aazoqo":["kassiopeia117","kassiopeia"],
"25xvwztn47ywzd7zjk2puj5s":"kashuza12",
"ozighwqrhfy7umxmwxjfrxux":"kashiru",
"g27bbp2ok5q22wfgxe4ojbfy":["kaskee","KASKEE"],
"vfi5jgnorko3z4mj3753ocfj":"kasai619",
"ylb6rlbuttejdijmf77dm7xz":["kashell","Owl"],
"nxblne4inbieyqwoxhiqzu6c":["kasichi","Kasichi"],
"pkwgdytemtnijhst5pv675xk":["kasilla","Marilys Vallet, aka Kasilla"],
"3sa5ww2mby3lvsm74qgpyjwm":"kassiel",
"eqf646dpli6yp27yiypcs3di":["kasiadutkowska","Kasia Dutkowska"],
"52x4igftdo4em5zvwuemynod":["kasperi","Kasper"],
"4tw7gsblic4zifzjv4r4e7tw":"kasssfi",
"d36ek5x5fyjpjzqdfphn2qrk":"kasperroszbach",
"be36wqre6qgetspsfkzpfpgz":["kasiathomas","kasia thomas"],
"dj2hnc2x62xjiwzcwpgtbeqw":["kascuga","Kasomi"],
"ob57uo3yfr3w3hlaqo3j2oeo":["kassandra9785","Kassy/Sandra 🐮🩵🩷🩵"],
"clrgrkusy52ytzjdyndcocra":["kassiequinn","Kassie Quinn"],
"cvzars6ohlvgp22ngzdcisjp":["kassiesdad","Woke AF Scott 🇺🇸🏳️‍🌈🇺🇦🇮🇱"],
"dnz2sukwqgqbhu4djxnnv244":["kasayuta44","kasayuta44"],
"hblsc2vsxiyht6qjnmzwq42j":"kashy22",
"dmixr23f3ekbnktipx222lhj":["kassi","Kassi "],
"fmiko5rtexscdpabhjmi5va4":["kashirou","Machiko"],
"anc5dy2tb4daa2zeqxqg7mjn":["kasuminakasu"," "],
"khqqxzr3ab5yep4yszi7342p":"kasyno",
"gp3b74zysub6l77hdvvdy5o5":["kassandra2703","Kassandra2703"],
"rgp2me3zpbxrdap37lmtfou2":"kashanskyi",
"imwy7w3b4noout4gh63b3mob":["kasingerj","Johannes Kasinger"],
"hwmuhj7lxconva7bgqhfpttr":["kasmanio","Omar Kasmani"],
"i5j6tn3e4o2jbgbtne6lvwpl":["kaslwood","Kas! "],
"3psu7xcyxxlpimdqivgsxapm":["kastro44","Kastro44"],
"ec5r4gck6t4ioltrwi2dy262":["kasumiy13","カスミ"],
"bw7ytusfkua4pxf4vzdqykii":["kasten","Carsten"],
"ero2wsxoswa2ypbsnw6gdosu":["kasslerkind","Sarah"],
"cnvxz3dkkdematjikbnrnmbc":["kasza","sasza "],
"6qqak2lu747wnfzy2lv7bcg4":["kasiafromthewired","Kasia from the Wired"],
"wp7z5x6g646qfrijjteed2ud":["kashkash","Beeze "],
"catsm5bvtya3buxzgrqxqwib":["kassiopeir","Kass"],
"v7k6n7kl2guwp6xt5ezv5yoa":["kasamuckel","Kasamuckel"],
"bhbe2uqcge2qyyzeno5xlbao":"kasen12345",
"leazmya733nqtynjfy7rwg7u":["kaseyblack","Kasey Black"],
"kldgusrxgudp5d3rgq5k5kfp":["kas20241013","Kas"],
"w7i2bp7ygagowcmrep27d7oo":["kasraabo","Kasra"],
"t4fwgjvq5eahxepgaj5hffsn":["kaspurr","Kasper Takami"],
"qmbrwauoccg3iphnnfiqas75":["kaslina","Kaslina"],
"3lw2gv4rvjcjadl475v7ue2z":"kashii",
"tfoeffed74mazpmepnmmuwhs":["kasorip","Kasori Project✨"],
"56bb4zz3y5gjg3sqlsiyi5wr":"kaschaff25",
"rotxyu4rc5r7rpu33ttbg4zd":"kaschult",
"qdzcrpjnzavazcqt65d645y5":["kashinoki","かしのき"],
"edqfyfcgus6czgzx4vei6l6c":["kasiamadera","Kasia Madera "],
"bxet3gyed6rrgjqhd4hwavzc":["kasii","Kasii the Avali"],
"njzjv5qqlzeafmakzvs3hht6":["kastien","Bastien Kerspern"],
"o4kg4dalsv3ddo2j5vqowwdo":["kasperarabi","Kasper Arabi"],
"gygnrybzxlp5hu5pax3hlkub":"kasch",
"lzozn5idpqv5br4gqayyhvv4":["kassiopeiakitten","Mystik Mayhem"],
"the4x7umocb2h3u4mxlo3oni":["kasiabesfud","Kasia Beresford"],
"g65a4vd2vw2jr5nsl4gtzydv":"kasemei",
"rqbwefeick4b5ozvwxx4lu2c":["kas82","Karri Suonperä"],
"5pubdq4p5if3k4g3j44hm2s4":"kaskamori",
"uzhuc2adi4nf34wgveae4nyu":["kassandraschwae","Kassandra Schwae"],
"rjy2ed6iej37h4oobuj54pkw":["kastorbleu","Kastor Bleu"],
"szze5qkbpolklzxv7w6ydloo":"kassia9",
"5sbcgdiblrpys26ukquciypj":["kashamaslo","Kasha "],
"rmnkmkupkftcoh2jiuwoua5w":"kasya",
"k7zsfksl7tfn453dgedmkd25":"kassum",
"4y2dh4qtgb3v6tbsab5ogoww":"kasiandherbooks",
"lo2wujcqwspquvcn4xohvr4j":["kassanovas","Kasey"],
"wqsw4byuszh53oundizjxnfs":["kasimirnemestothy","Kasimir Nemestothy"],
"gqav655ueymue35mvcy2hfdy":["kaspitania","Kaspi"],
"mbd4kegqhm2jsmgluzekyo5b":["kasdamderg","Kasdam"],
"2egs4y37mlp4u5mriso5m5da":["kasiaemerald","Kasia💚Emerald"],
"htkkcwzcdqbj3bsst7scffki":["kasperweigand","Kasper Weigand"],
"xyyptncgvpvguzpglkytzfye":"kasuto",
"45555mx4paw7ppj63c5zfntl":["kassiastclair","Kassia St Clair"],
"eko7pkt4eyifh4j2mapdktvc":["kasukhova","K Sukhova"],
"xnhxdgj56auaekq6ofbsnzpm":["kasiamojescik","Kasia Mojescik "],
"4zhalhcsxy4tncqv6kdmqlil":"kasu33",
"d72tm3djdf7273frvlduon2v":"kashue",
"xgnxi37c55ubnxwnrlydizl5":"kastanjalintu",
"ulz4rbirven24erxkjp4ts7p":"kashapau",
"clepovpz7ivffqxseuaiuk46":["kashichirido","Kashichirido"],
"d33b2xcqrw5rriktha2wgmw5":["kaszia","Kaszia"],
"bfcz5fubogjy7ayhxymw5w3z":["kaskaderegion","Swirling Seasons"],
"pvoqssc4rxahbr6xiyhpx6my":["kaspernissen","kaspernissen"],
"aljjhbjlfyfpcyzdlti6xvpy":"kastenfrog",
"bwc3wcyrzomnqahai4xmp7d5":["kaeoni","Kash 🌟"],
"5vimp3troyd6m5hpsm52jw5v":["kasz","♛ 𝐊𝐀𝐒𝐙 ."],
"bykjnppvdofnzs7vilplnem4":["kasurinenriina","Riina Kasurinen"],
"3j5kwjyw3kfzq2kkwdv7akrb":["kasus","kasus"],
"zod4kym733sut36wmg6fqw2q":["kasharic","Jamie \"Kash\" Sloan"],
"33qmsssjlq2u5s3czx7dndfi":["kasst","Kassandra "],
"3vxcam66spp46jmoeds4fj4d":["kaspergoossens","Kasper Goossens"],
"oy6x2pfz2wvmwbm7eyqv74xt":"kassmaster13",
"4vmptiv2tiwgsoceoyy3a7nd":"kashubia",
"iseaqzdhp655chpjrqve3aj3":"kaspercoei",
"4cw52ok25gv347enc7km4rna":["kasbahrock","Caspar Holtmann"],
"krmvsae2yn3j2xbekvgnavgv":["katikasanen","Kati Kasanen"],
"cannipfs2ab2isysu725sjvi":"kastenweissbrot",
"oy5rftttrhincivet6odhfrk":"kashen",
"a3ndsxiil74qlqr6vodo4xsy":["kasjorys","maple"],
"2cjpcxi7vmtlxdzjw3gtnxut":"kassiererwilhelm",
"4yh7uetkni5u66xp36us6ox7":["kassypersephone","KassyPersephone"],
"cxzgf5biz5uh35sav7svdei7":"kasuskasus1",
"elcrt56csqxjkyo3a3abnerv":"kashira",
"xs5px3etywlypea4x4saj7jg":["kastark","Katherine Stark"],
"zode73u63xrpb4mopqbgvpyu":["kasui","珈睡0時"],
"rpbuprgaguawuo4prdjjbaxa":["kaszatycho","Kasza"],
"mwowq57mr25l7fhxhjityias":["kassandrra","Kassandra🔥🔞"],
"bsw7cfka6ihvzxjsm6n7e6n5":["kasenkanesada","歌仙"],
"3bmd62gn4tp2cnp6bcacfwqj":["kasatushi","kasatushi"],
"wkdtfvfglps5w5shpb7b2r76":["kasatikpolosat","Касатик-полосатик"],
"wp6bsznkfstp3mzjq63ll2im":["kassey","Kassey"],
"awh4xavsvcesnfildu2uzeoe":["kasumagaladriel","Kasuma"],
"yhvjwemyyjd7j467qemhmo2u":"kasaikaibun",
"u5o4wcfn5ru5s57ivx22ji5o":["kasiliashirika","Kasilia Shirika🍇"],
"r2psogmtgvr3a4glvhpgg6uq":["kasiakasunka","Kasia"],
"btldz5sgb6fgeqpr34tffonp":["kasumiyoshizawa","Kasumi Yoshizawa"],
"keox43cqcriqoamwmnqom3ry":["kassikassikassi","Kassi"],
"jscgdittcq4ql22jsptm6nie":"kasolotl4113",
"c3ekfnh6k2odudoopru2qmuq":"kaseym94",
"txpcdsmg6lbovfboq4rurjwp":["kasch17","Matteo Lukasch"],
"zrm7xdwx5amup7pcwgnyozli":["kaesebroetchen","Kasebrötchen"],
"7iwdnzlxb3lueskzzuvlxv5g":"kassendal",
"uyxavsrodmr4c4vpk7o3jjh2":"kasuga675",
"ev5pyqtqbkgfjjpxrhkzza4f":["kastenmauer","Nick | IBJ8 SZN"],
"qqiyqpc3vs4kwezu625tdm5f":["kassthebroken","W I F E 1 3"],
"ohxjwsplpwcimdd2jhfuq3a4":["kasperkring","Kasper Kring"],
"ctyeldbfcm34muh5we7wp2if":["kass-c","Kass 🔞"],
"ul3tsytdxr7mfrp3hgl3a2wp":["kaikasaivt","kai_kasai"],
"objhu77wcsuadpjvpablz4bs":["kashusb","Kash"],
"ayfskfrab6enxsteim2qct6i":["kasozishafil","Kasozi Shafil"],
"4h7x5wylzfa4dubyskuqljkp":["kashiwafox","Kashiwa fox✨️"],
"yejafzzum3jyrksdaesde6wy":["kasdeya","Kas"],
"yyxh35gunvdpsgasdvbvba2b":["kaschi87","homie"],
"xx7kuk4bqv5khzn3v6xqa36j":["kasperwithak","Kasp(her)"],
"4migpswqllgigxmaxb72r6dn":["ka3uka","KASUKA／ブックスエコーロケーション"],
"2tuqdc3huvqmkqhognaxfyn3":["kasiainen","Keke 🇫🇮🇺🇦 NAFO Space Force Fella"],
"ulzzmkra6shr6w6z7j7cjt2r":"kasperhj",
"kwb5b32lclur4vfwrdkow5io":"kasper89",
"qoy3u7tuocpefaanctyremtq":["kasomephisto","Kasomephisto"],
"sn52ubpebumm4huadw4zusrx":"kasendwa",
"rjja7ywcj365aohgq7kmvkcd":"kassandr4",
"bgjvbqszngei7572nizkdtn5":["kaskman","Aidan"],
"fe4coqhltcwd7sq3irquizvs":["kassiano","Kassiano "],
"2xnce3ccbqbhmspgdkrwcalw":["kasutoproductions","Maxi Rodriguez "],
"ebgovpmld7zcvd3nfawh5ba3":"kaszast",
"az6yh562oapxlbyega2numil":"kasparslans",
"otacfqxzhpnh4jfunvw7qvlu":["kaste","Gremlin"],
"dhkdposmogbgexmguminc74y":["kasetsuna","Ka.Setsuna"],
"wmvnft54fstpqoqqm6ztp7mj":["kcdcwrites","Kassidy Coursey is still wondering what we’re doing here"],
"our55dznslycb3qpnljh2mvf":["kcpregler","Kasey Pregler"],
"uzdhxplc5niggsqaorvejpqn":["kcthemeek","Kasi Meek Kennedy"],
"glzbbisjmwu6yq3bkkd4ygcw":["kcadventureco","Kasey Fagerquist"],
"dk3sxie25fswlt7q3zgqfzsd":["kekecoyotl","Kasper"],
"hkvhc2npfsrvbrt4aoiiu5os":["kenji126","Kenji Kasahara"],
"3gy45k64wuefvk6g563nx5lq":["kellianne","KAstros"],
"i6zcrvsdne2itioocg6ujjuw":["kennykashew","kenny kashew"],
"lszotfimaq2rcwn7xlt5urn2":["kfowlerfinn","Kasey Fowler-Finn"],
"sefqmmpcwvdgxv64uv4wuvwk":["kgossink","Kasper Gossink-Melenhorst "],
"ypdawssno6bxvi6c6tdth3rl":["khuyen","Khuyen (Kasper) "],
"okduhxdoamr4hpcuitmxyu6a":["kianakaslanav2","Kiana Kaslana"],
"ccq2xegjupypkk6vc3szkeny":["kissedkass","Kass :3c"],
"tiqcvy42ytysllh664jr7iqr":["kirkwhore","julia wants kas ll 🦇🧛🏻‍♀️"],
"spxtpdgwv7shy55ybifof5as":["kittyfication","Kittyfication @ Anime Festival Kassel"],
"nhrbfrfc3477tx32p4zgf5it":["kikikasch","Kiki Kaschock"],
"554j547uuo2jacx24e5ckh4e":["kimskwing","KasinKim, No farnarkling around 🟧🌻💙💛"],
"ggrqptlwv3dnl2aozodvjovm":["kinoimkasten","Kino im Kasten"],
"uak6gpgmsfddw5e7767hsn4k":["kjonge","Kasper de Jonge"],
"mzz36v4wdxh5d3wlhcwyvobb":["kkstrk","Kasia"],
"iksw5563bjdmdcug73ibdak7":["kkashushu","Kashushu"],
"wguv74sdpg5o6rjjj6ftcldz":["kkasai","Ko Kasai"],
"vpk6dmwl5v5xkclicoki2fso":["kkasiu","Kasia"],
"pksgcjdjqe5wcy3b6wvoqrio":["kkasianenko","Kateryna Kasianenko"],
"d5l4s4g5p7vbyidafljr256t":["klcombest","Kassandra Combest "],
"nz2bvnddgbvmt6xv3fnqm5xq":["klaushiena","KassHiena"],
"gjcmgdbyy45gtnqzi4wisjwc":["klauskasanova","KlausKasanova"],
"lgvwemvdsq6nhvbg62zw4hur":["kmforest","Kasshoku ᛝ Forêt"],
"6ou534nq6sw3xzwryqqiy4o5":["knoon","kassidy 💫"],
"lpty677bzflaky3fdr66m23d":["kozmicdonut","Kass "],
"ecqksqqr6okpxcnebocbprq2":["korikasai","Kori Kasai"],
"74jhq6qsl3bgseayo6trs4ux":["kripshen","Kasımsu"],
"54lvyq7dgcahxvabnfaviku6":["kriskashtanova","Kris Kashtanova "],
"ecsigk44mfrpsvpvwcooskht":["kraux","Kas Raux"],
"2rl6yrtumuk3z2jpeiphokyp":["krogh","Kasper Krogh"],
"am2yciayg4ahru35wqo2ovj4":["kristinekasuka","Kristine Kasuka"],
"ste7uq5f2dcmprv5ja44skvr":["ksmbits","kasu"],
"kxzuh5krinvueozluev6jxwk":["ksw","kashiwa"],
"j43yz46bojzxcelyb4hfkr2s":["kshf","Kashif"],
"pmb6jxv6z5fkvka3envwlqvm":["kscribblz","Kass!! ⭐️"],
"dlkluotqiwwcgerzka5ze6el":["kspr","Kasper"],
"ggqwfxw2rnu7d7azzr52xhn6":["ksurber","Kaspar Surber"],
"olw34cmn7u4kp5hp3uyv3exa":["kstanton","Kasey Stanton"],
"lyk6j553snci62tjjfhoviym":["kshmir","Kashmir"],
"uhtc4kd7ciedkotfx4f5ho6d":["kursephone","Kassandra, Simic Possum gf"],
"g34o42mb4ftcdkbv2ioqbmx7":["kvbb","Kassenärztliche Vereinigung Brandenburg"],
"vbsl542msmwj5msgmf42a2zx":["kvwl","Kassenärztliche Vereinigung Westfalen-Lippe"],
"uwryyydpbrwsw2sanpsxzi6y":["kxflavio","Kasey 🏳️‍⚧️🔞"],
"qmk7tgxigtczzifmc3dg4qde":["kyamaza","Kasumi Yamazaki"],
"tvrzpbhi4qcbuysrykj7rx7c":["kyojikasshu","Leon Kasshu"],
"exn7tljl5rwd35v4aqjzsclz":["kyassel","kassel"],
"liuejnqp6nfxef67nmbyzw22":["kzkedzierska","Kasia Kedzierska"],
"ej7len6aqbafuhkjzi6wdfvz":["lamaredia","Kasper D.L (Lamaredia) 🇸🇪🇩🇰❤️🇺🇦"],
"muuhndfuofu7vk2hpmqkhsln":["landmark","Kasper Landmark "],
"k4hlvjdjeyduum6hhy46ln3y":["larskasper","Lars Kasper"],
"m4illkildqgxnvnwmv6bfnxq":["ladhylian","kasiarya "],
"4kh33gn3p6favrmdch5mdvb5":["ladykassandra","Lady Kassandra"],
"eaectrae3d5incecqju4ahk6":["leekassen","Harry Kassen"],
"ppyvbsslxu2yswf727csp3tw":["leilakassir","Leila Kassir"],
"un3y3vd5psijwskdfwahcdng":["lena-kasik","lena kasik"],
"yzhi2bizv6hxgm4nxm3mzilu":["leasdef","kasey anderson"],
"hwwlkemtq2lfm7hxkxp5zvhb":["leekasper","kasper"],
"qvt5rrrnznkjawa3xhqrt4xb":["lewent","Levent Kasapoglu"],
"pyanyrmqoaxouucrceinrfat":["letzterunde","Kaspar Keller"],
"q5jyvspv4xrdthlgg3kch3fe":["legadovideojuego","El legado del Videojuego (KastroSolid)"],
"tksjehl4cblo3tv6koq5zpwp":["lilykasai","Lily Kasai "],
"jfco6kh6z5g6tvbertlqm5il":["libertarianbee","John “BlueSky” Kasai"],
"fzg26u7susdhvbuvvzqzlv3t":["liveson","Liveson Kasenza"],
"qb5x6wnvtn7wxylrgi422vso":["lizziek","Liz Kastor"],
"hg4ve2s6spd6udbbcdkbnqey":["lindsaykasson","Lindsay Kasson"],
"b7ebhxbnxqy6b5jb2mhrzdbr":["linhuworshipper","Fukai Kasai"],
"ixznl6idhpeznyerq2spjk6e":["lilbatvt","‧₊˚♡ kasumi ⠇bat maid vtuber ☁️🦇💗"],
"3qmm7pj26l5d6sxzzwypxo52":["loonymoonie","Kasumi 🌸 かすみ"],
"hybwdusysxnzccy72lh76uvj":["lordkas","Kas"],
"mdtg2un3shajluosvf46pyyz":["lobna89","Lobna Kassim"],
"2ad4bxyfz4ck6rbd6l3zdkqp":["lukasmitk","LuKasMitK"],
"6izmqs3lvwkf6i37rj3lmm6d":"lupinx-kassman",
"j2ppbb5cdvmluovjzpvmmdfu":["lukekasinger","LukeKasinger🌿"],
"q2azjk2x5pof4sf3dejvrmo4":["lucifader","Kas 🖤🏳️‍⚧️"],
"v3ptcqz2sybqiapj7flz4l3z":["lvivska-kashtanka","львівська каштанка "],
"qck2b7u6g2kes5hifol3bvrh":"m4kas",
"266ipbyio26nsizfg7avheuq":["marykasprzak","Mary Kasprzak "],
"naoyg4l3tki2uibom5z2y427":["madscientistphd","Michael Kasten"],
"qlvmrwiqs6nbtq4l2xbclo75":["makomako","makoto Kashiwagi"],
"kjys6i7wh7xrhemrq5qtppw2":["martinkaser","Martin Kaser"],
"kfy4poj5a54rbjed3xxqd2ql":["maksymkasianov","Maksym Kasianov"],
"bohpsc2byq3wtqh66ngi3wdn":["mangakanekochan","🍒🍊🍋 Neko Kashi 🍐🫐🍇"],
"6k5pubu7epokeqozixkkthih":["mashamasha","Masha Kasha"],
"ohm6ijstcdml5xmvsn6wrkuy":["marcin-k","Marcin Kasiak "],
"nvexmn7o4yn5zbj3pe4irogp":["magokastor","Mago kastor"],
"kodrkoxanuqnmx5xchjqhmsw":["mahdikasra","Mahdi.kasra"],
"knre5pcw3nmadxei7ukmtirc":["marchemis","kas 🌷"],
"z7psoomtcnsnonfl6xbunlpm":["madkas","Kas"],
"q3754mqiqnvcegqydgoeoxdw":["mattkass","Spooky Matt Kass🎃"],
"dfzucbbnumicafyzrb3kpm6r":["mazee","Mazee Kasurame"],
"c3vixhxenpkl4363vhtseawr":["mamakashew","MamaKashew"],
"l2ppouws2ihynolz5edbxovg":["mckasty","Michaelangelo (Mike) McKasty"],
"kc3cvjw4w7f54zr37l453sbi":["mertkasar","Mert Kasar"],
"yjds6l5b3mvtfu4npfz45whq":["mehrabani","Kasra Mehrabani"],
"zs7r37up6bc7y3xdc5fgd5xn":["meherkasam","Meher Kasam"],
"nt5kpvc5zcbsmxxa27egzoqq":["mekelkasanova","Mekel Kasanova"],
"qjfe3h6ypfov7l6oywogt4zm":["metalepsor","Toni Kastanio"],
"acz4h3denzya4osozawcrkf7":["midroadman","Arm Kasidis"],
"wnupv4xszpbt4n2inxhb3yzv":["mikekaspari","Mike Kaspari"],
"sglkfr3dfot7pdguzp7ger7e":["michelkasprzyk","Michel Kasprzyk"],
"evohrgq6x6f5q4udrzkpjasd":["mikaelkasurinen","Mikael Kasurinen "],
"g2kdzeennpdeo3rrddmire7e":["mike.jammer.social","Mike Kasprzak"],
"spwwvrlfjhvparmvbht4cbcw":["milesmithrae","Kassandra"],
"to6bkdofe2ci37qwm6cettha":["mkstnr","Mark Kastner"],
"ng5w4fhze6nxhseysk3keuup":["mkass","Marty Kassowitz "],
"6pz3diwbg5spjnnwqz5o3avi":["mkasu","Marc A. Kastner"],
"cbtr7cxafohnio7dgpgx4sx2":["mkasper","Matthias Kasper"],
"ooeijwqjdxpdeignpfgpd6u3":["mleadman","KasperGutman"],
"ms3qx3p5w65lwzflpb2zv5gf":["momididori","auf Kashima wartend – nach Naruto rudernd"],
"xzap6g76hbmsx446p7umuuf6":["mothbrainz","kas"],
"vhmudrbatrpp2d5n5xw4nngm":["modshippy","🩵 kass ✨ heard coney island live !"],
"ukrbkejkpakbcazkd6ylb2ga":["mortalkastor","Kastor"],
"bvilqshinqp5ytm6i23iwusm":["moealkasm","Moe Al Kasm"],
"mocbkosjx6t3vnaph76hsh6a":["moonwitchdraws","Kasei/ Kas"],
"pxtyenei2ntqlwdhcwlnxd7h":["monstergoop","Kasirith"],
"pfngag5oimnj74ddzirsbaui":["moneontour","KassenMone "],
"d2fl32jownfjuq2mptc6wbtx":["mrbelievers","Kasahara"],
"ppitbl27h45undds2pt3kuqm":["multiverssio","Kassio Veras"],
"2dh5lxthggxzzoetrjmfk6ua":["muntangalng","Kaseidy "],
"pend4737yuzjukwprvq2ytaj":["muzafferkaser","Muzaffer Kaser"],
"m4bqpwexaseysljjt3vkwn75":["mumukasper","Mummu Kasper"],
"m2jubnv3v2l2alf3dt45cjwy":["mxedchaos","kass | chaos "],
"m7ph6wxlodlf2is5y4g64bwf":["mylloon.fr","Kassoulait"],
"mgjx2iq4t4kqsuwtvqrtev2d":["navidkashi","Navid Kashi"],
"yv5vpkczfqs6wwowpx2aqrln":["nandokasteleijn","Nando Kasteleijn"],
"zh76vqhi4xjuqzc77cmgeapm":["nabaxo","Nebez Kassem "],
"ixqxmgzhyap4z6lgiuxuqhpa":["nachingkassa","Naching T. Kassa"],
"2jmgvchza5rrnnc3g3bp4ge5":["neptunescribble","Kasper"],
"bpfmrzppvr3lpebabjdkr77l":["netzbeschmutzer","Daniel Kastner"],
"dy6cpi7lgxuvtrydk4hk7u5n":["neokashunexus","★KashuNexus★"],
"oqawtotpan427ny7qcbbdmjv":["nickamandra","Kassadra"],
"cqpporsqfe4hl3y2dbcv5iiu":["nilskastenhuber","Nils Kastenhuber"],
"yfrdfxm6fzexnydmefo4p2i2":["nighthorizons","Kasey McKenna"],
"4nui5xmlfczqwsdfeanrm4yl":["nicolekasielke","Nicole Kasielke"],
"ub3ixbahmicrt5rifg633ken":["nmoreaukastler","Ninon Moreau-Kastler"],
"3uzaf2w5ttg5zxofmn6pgn75":["nodebotanist","Kassian Wren"],
"myipnf6xnd54jhuytyaqic2g":["novitiate","Kass ❤️‍🔥"],
"xmrts2qkpnfldwhxbt6v34hf":["no1kashira","두목"],
"idme26zfzscakrd7xiwyj5ow":["nyosproductions","✦ Kiba Kasota ✦"],
"sgf7fqq5vzfsg6oqf3tez45t":["omarkassim.com","Omar Kassim"],
"ap2qj3lbi4pkf7l252giu5s6":["omisoumai40","kastu sonomi　園見 喝"],
"cztj676sn3hxbgbbyeqhykiz":["ondrakaspy","OndraKaspy"],
"jgw5t6gn2ust3da426rsgfy6":["oniikami","Onii_kami @Anime Festival Kassel SONNTAG"],
"ksjh4g3k6exw4ykf5opzegml":["orbitingkahei","kas"],
"oehpfwswqttkz3zriqr7d5j5":["outkast9","OutKast"],
"dwtlhdnjajmnvpdvgvcoldhc":["p0kasokas","P0kasokas"],
"3akztazi5fohupfqjpes6ktr":["paladin356","Pally Kashra @ Home"],
"nsgw6guckfd267vc7cmrhmn3":["pannan","Kasia Witerscheim"],
"utlb72mek55rudedg7lut7ls":["paulkashmann6","Councilman Paul Kashmann"],
"2yfnpervyoyxec25afd4d5cq":["paddedsnep","kasey"],
"rt5lwcnjpmxjzfjbmmcqfrto":["pacificcoasthockey","kaspershark"],
"2gmwttasdu2lon25rrrmsoad":["palaverhabarber","Kaspar Wrobel"],
"2p5f7e37w2q24q64zvejk6ej":["pend-friend","🌈🏳️‍🌈Kasha's Local Menace to Society🏳️‍🌈🌈"],
"gjgt6fblk4fdfao6ggrekywu":["phagehunterkw","Kasia"],
"odv72zcx4kjn5elr7mwtyccu":["phantasmic-kas","Phantasmic kas"],
"ql4xdzfzq4vftn34t243zklr":["phillipka","Phillip Kaspersen"],
"dlilow5y2q5kvt2hull4eq7k":["pissbxtch","Kaster "],
"374ndvsgyd6zh3n2dznt3rkc":["pivtora4ka","Pani Kasya"],
"75bf4yxcz3dcdqxelgtwow4s":["pkashwan","Dr. Prakash Kashwan"],
"dejkcrv3jxszhjjummngygyp":["pkasirim","PK Kasirim "],
"n5ltrrduqcyffdvj4xo5sgd2":["polyphonetic","Kassandra"],
"ar6dhnw56frpshkxtbosulmu":["pochodnia","kas de la fère 🩷🐳"],
"ij4rolfadmlqz5s7tfjzawnx":["polarkase","PolarKase"],
"z7qea2shhudjpmtizkwwyg5h":["preiskegeln","Inkasso Queen Kassler"],
"vvnv3q5jxfmpz34smgyn2oho":["prodelkastineo","El tito Kasti"],
"yzt5y6u64c2zbg5cmkrupfzj":["psychedelly","Kasia"],
"yfqsdr4i6spn6gvwhhetce4v":["punkey","Kasey Kagawa"],
"ahvfjoaguhg6r4icetawfot3":["purpleghostkasper","Kasper"],
"hcuwiqh64bqsmqhhxh3jmtnx":["qrrrn","Keren Kashi"],
"eb35iljqwzcfh52s3rt3oo6l":["qunfuz","Robin Yassin-Kassab"],
"doq62c7hrajnekrfhkvtrngt":["quasiulysse","M. Kasiulis"],
"4dk2qfyidf6cnk7ljsv6be2y":["queenkasaga","QueenKasaga"],
"z6pn5brs4dszrqekhsjh7lwv":["quasey","Kasey"],
"esuad2t2esohq7taicvwzyjw":["qwerty123","Ihor Kastuseu"],
"h3a3gr7b5pjohyjkjhveotfa":["raconteuse","Joseph-Kass Tomaras"],
"va7iq7sslymaq4k72koxnb46":["raytheonpride","Kass"],
"7jt2v5pp4pxa2kjby2vmnzeu":["rachelkaser","Rachel Kaser"],
"fa57jeh7agptobqzjadb5osn":["raykasuta","Ray Kasuta 🐰🥕VTuber"],
"jeginpxmob5ffpug2zayyvr4":["randomattempt","Kassie🏳️‍⚧️Resident Fey(She/Her)"],
"gku46sbr5oaeclcb4hjep3ww":["rafaelakastor","Rafaela Kastor"],
"d3thw6r4ab2mqqjgbmsrnqg2":["raskass","RasKass__"],
"yxvzvbirtwnzxom2hz4pvem5":["rero70","レロ/中村香住/Kasumi Nakamura🏳️‍🌈"],
"qajxybxgj2lz5z7wynw3nd5t":["reisho","Reisho Kashiwame"],
"3q7jzxd4eeqvavtqj4ojrhnb":["reidk","Reid Kashmanian"],
"3eis4z7k5vrochfnt4b4zgzm":["redredredredredred","leonard nimoy's \"kasha varnishkas à la vulcan\""],
"dqbazcq5ukjnpwkcyawhqt52":["remikasprzyk","Rémi Kasprzyk"],
"nvyebqohd42a2gp2bhedqw2w":["reeskassen","Rees Kassen"],
"epyrzq33bqhfojjgfjap7okh":["realkasumi","RealKasumi"],
"wchika5mszznjwblrzuazwsy":["riazgameaddict","Kas"],
"73fhxrspt4b622w447ru2qgg":["risupon","リス // Risu 🧋💕 @AnimeFestival Kassel"],
"lqmdpie3y56wh2txqknleqj5":["ritakasino","Rita Kasino"],
"4axlk4zllfwdbh2erqxhyp3l":["ribellapub2007","Emrah Kasım "],
"zoyzaoepq7cum75k5ydkygqm":["ronste.xyz","Kassandra ihr Bruder Clifford "],
"2ab54nxn5w3xmhl4kmnyxbr6":["robotanist","Kass"],
"zij23opr2uamoc6onklquzbu":["rosyfaced","kasp"],
"no7yhtwc4nq2c4zw4itdfxqo":["runesalt","kashio"],
"i53cuo2776ikxzmfu2kj4btw":["ruthkasdorf","Ruth Kasdorf "],
"spil3h5djt4npyxl2ccx3lon":["sarkanymacska","Kasey meg a gyalogszőrös"],
"umx4zqzhu2thpbi4ptyk7be3":["sanketkas","Kas Sanket"],
"k2ncnsb4cv7m74zvpimxb42s":["sassykasse","Stasia Kasse"],
"vqwlh4hlfvn4bnnifshiegme":["sarahkasbeer","Sarah Kasbeer"],
"i5ovvmtasahzfvl3p4hwo2xl":["sapphirecosmos","Kassie"],
"pqlgmons3gsremgtlgaw4jqo":["sannakaski","Sanna Kaski"],
"lzmdmmdfj5p7hwfxogwsjt4d":["scottkash88","ScottKash88"],
"pj4euujfqxrfikrnhxq2jcoy":["scullingmonkey","Kasia "],
"bukgdlgq3d334agyyqgdnmwt":["sciphotogastro","Kase Jameson"],
"24q77ex6lxd7jrf7igpbkpus":["scooterslounge","Kass"],
"5jo7i6c5qdeux7fex77twfvn":["sef","Seth Kas.ky"],
"4s53wkhjn2kprqysaqeifq56":["seozen.com","Kaspar"],
"fgxussbp3aaie3vblp3wteoy":["sene","Enes Küçükaslan"],
"6bqq6kbnk7yemuxnwc2siv3c":["seasonalsaison","🧡Kas💚"],
"cic5a4hlxjc6v35kd2knjxi7":["shiftingdreamer","starlit silence (Kassna, tired)"],
"d7yprune6li2qkjcb25opt2r":["shib","Mohammad kashefi"],
"kybcdlpvovbzbphsqjtoty6f":["sharkkass","Kass, certified Megalodork"],
"joq2jkmt4w2vnbgnbvbsryfb":["sharkiebites","Kasumi"],
"quciitvjyezjtz7yw7rzy26l":["shiraikasumi","ShiraiKasumi "],
"f745ceiav3hqvnes4vsv4niq":["shishino","Shishi / Kass"],
"4actcyxljttu6e7j55jdfjri":["silfire","Ingo Kasprzak"],
"fkw4w6424tetowzgcjosmzbd":["sirkassian","Kass ._."],
"cwrawkm3nxcdm6x6xrrmkdaj":["skastberg","Samuel Kastberg"],
"4inff4bednt542o3ipsmmn5p":["skinworms","kash 🌻"],
"f6y7lzl5jslkfn7ta47e7to3":["skasper","#LeanProductivity 💎 Sascha D. Kasper"],
"dlrwfh57kplvszfpu5zegxx3":["slava","Slava Kashanskyi"],
"jpiqtltlczahk3qpvcil6tgg":["sloveniesta","Marcellus Kastelic"],
"it5np234a3thnnrns5xtqblp":["smkasman","Shari Kasman"],
"cgxedpie7577bwnb7imer4y4":["smnsays","Kasper Johansson"],
"ngvmnn7sa4lginrxwuadso7e":["sodapoptops","Kass 💫"],
"ibvxorunkbnngxsj5scvyg5g":["sonikast","SoniKast"],
"mu2iewzvdsms4m3pdfbtuqta":["soulcloud","Kasai Akuma"],
"yu5ihcnlkc2gv5mc37jjricj":["society2077","Kashtira Hater"],
"iofebdqmhd3adc6apz2knna6":["sorakasaivtuber","SoraKasaiVtuber"],
"7lrfu2ymswcuh6vttbthg7xr":["spacekase","Kasey"],
"v42vbwhdxvo6am5fnom6fip3":["splashkase","Ash Kase"],
"qhptg7ge32txpsvknx6lrbur":["steph","kasteph.eth | kasteph.stark"],
"t2375ysngur3gs6w45nnl3tz":["stevekass","Steve Kass"],
"oo56l6cf4zhqxkndpvfu4scn":["stefankastel","Stefan Kastél "],
"bpvl6hqsdubkws5m6jtjxnfz":["superkash","Tom Kash"],
"ostfrbnfa5lohaf7pv4scwqv":["suma90h","Shuzo Kashihara"],
"4jsklt4uderebom7bafg2asb":["susanbk","Susan Blumberg-Kason"],
"ka4v6n7kzcgg742xwetjxq4h":["successfulartist","Tristan Kasten Krause "],
"4qswaf2esjtviotcmbo4kpng":["suspigt","Claudia Kasper"],
"j6rw4feto7hbeeevydpcmpkn":["sunokasai","SunoKasai"],
"xrc6j2nssfyr26tap6kbr7tq":["svenkasser","Sven Kasser"],
"a4u5qzq44n24cm7vwsx4xoas":["swkasparek","Steven Kasparek"],
"mdkmklfxf3hekilgizky46sp":["taqkasatmata","Taq Kasatmata"],
"e5gmdsm2kmx43ka4iaa46fgt":["tamerai-shuffle","kash."],
"njprvirbeyv7pfgl3kbfjiv3":["teefykas","kas"],
"ocubresoppaddlc65f35zrr2":["teilzeitotaku","Teilzeitotaku @ Anime Festival Kassel "],
"5awcylmoj6ydr5led2kvu3iz":["tentakoo","kas.⁷ 🐙"],
"cthqxuqkosrxr4hcxr63z7ed":["thekdd","Kasey"],
"ejpzg52b5dtwzfxiuk64kxgj":["thestaticman","Kas"],
"7cavvgwkvtecbc57srxcrsnb":["therealkatburns","Kat Burns ✨KASHKA"],
"lsahxpmoleagizwk3kv75ysc":["theolddictionary","Kasty"],
"pjj222gfuocwwestnlgrpiz2":["thekasalka","Kasalka"],
"l6md5og3ytaofguwntyh2xge":["thisisksand","Kassandra"],
"ws4rdlbgqbn6ejxxonml22fa":["thekaspar","Mirko Kasparek"],
"swpivxvkmaezin27nt53g2hg":["tinyfox","Kass 🦊🍂🍄"],
"7okljl4xb24zfbxlyjghjwgr":["timkastelle","Tim Kastelle"],
"cozuj6v2f7a3vmqobp6wepwf":["timkasai","Tim Kasai "],
"c2cuzyf3xjdmdos2krblf55h":["timokasko","Timo Kaskinen"],
"a3pjpdlfxheektcusy5pupwc":["tjkasperbauer","T.J. Kasperbauer"],
"dci3g5oae2f6gmzdi5ic4mpa":["tkasshanna","Tannous Kass-Hanna"],
"iqelqsuimny7bk4lw4tpeiei":["torbenkassler","Torben Kassler "],
"pnayuvz3bnnw4fmrrwfsltln":["tomaztsql","Tomaz Kastrun"],
"cyu6vy362kza4raiiw56nlhj":["toshiutaton","Toshi 💦 @ KasselTreff Sonntag"],
"f67fkwfl24ggzaiem7djou2d":["toddkashdan","Todd Kashdan"],
"uxzbbkr22f32ef7t6emxb2iu":["togzhankassenova","Togzhan Kassenova"],
"o6hbsnbz4juazdeng3nyum4j":["ttimemachines","kass!! 🪲"],
"jgxgeyukovvqururciyjc5i6":["turtleosx","Kasper"],
"mbz5dlu7pcodwrco3xuqzhx6":["turgutinnc","Benden başkası değil"],
"wddlp3zzbukakvkrvtvauusu":["tytygigas","Kasey "],
"bfpmpfbicenti4qcxccpkd4l":["unthijnk","Zar Kasmus "],
"izlfez7mk5u7yvfafwwargdi":["unpressedtofu","kasie"],
"q5ilyh5gr43a4volnuxcoppl":["uniformshark","🧜🏻‍♂️Kashi 🦈"],
"fmunrscsua47f3s26zpjlus6":["uncomfik","Kasra"],
"plta6mddycinr74bqwkbesxt":["unikasselunbefr","Uni Kassel Unbefristet "],
"fgeq2dizffyipzyax5q4gzc5":["unndeadcat","Kasperino"],
"652r27imesvhonvqbelvqyga":["upperkase93","Kase"],
"biisvccynzd4sdokwe24ozt5":["uraz","Uraz Kaspar"],
"sxkmnr5xmnns3a7jyoyxbm4b":["vanitasaurus","kas 💫"],
"vxx2aoeecvdwn2cm2ajejtao":["vanrijn","Jason Kasper"],
"qbi26dpfn6rrld6qblpmv2zj":["vasiliky","Vas Kasidis"],
"rczxzwaf2qsd5idmusjktumo":["verkomy","kasia 🌱"],
"pgs7auzkh4jwgci2rp6a622u":["vinaykashy","Vinay Kashyap"],
"pj4dqkfkuuylprkpwvcbv3yq":["vkasahara85","Victoria Kasahara"],
"ptmzimd76ktvbss22vctaeoe":["vkasch","Vinzenz Kasch"],
"optxsbhyutp25it245ltcyts":["vole","Kashiwagi"],
"oi3nckbldhi42lfjdt5xogcx":["whatever","Nora Kased"],
"nb56zqy6zsivw56uyqgn4eqw":["whereourblueis","Kashimo-ist | Ace / Callisto"],
"i477auv67t3xtzrg6v6zfksk":["wh1tewolf","Kasper"],
"mqsqu3nx43i2t2uwjmmkbbgx":["windflowering","kas 🌈✨"],
"zteoc2ochzdrj7wzyq3233cz":["woeart","Kasia"],
"6rhi4ld36whw2kvoqdgxfug4":["wolffleuret","Kasha 'Wolf' Fleuret - Support Human Artists 🎨"],
"x6ihrqtymfapeejc4lqfqctx":["wooftopparty","kas"],
"lwzoluauz4tb77esxgyor6ib":["wolframkastl","Wolfram Kastl "],
"b74va4xprylgarjiixs2qqng":["xandradoodles","Alexandra Kasenda"],
"fx2oob2kqt3vhg66cyr6dzeg":["xkaseyx","Kasey"],
"ekwkfybxqrghq5jhp47kddpg":["yedibolgede","forks kasabasi ozlemi"],
"rr2hydt3la4tx3s2ckg6oezf":["yeenergy","Kassie"],
"qnyyo6cbuhw7tck3cxxfk3zj":["yikesbabyy","🩸✨Kas✨🩸"],
"opxsttf6m4few3d2sgor3h6l":"y-kasa",
"qqadpamszrnd63sdsvygdnps":["ykashtan","Yannai Kashtan"],
"p33r7kcloae3rwe65kjsucvg":["ymasha","Mlimova Kasha"],
"do4iqvbg7uv6nec6sfjpegln":["yousifkassab","Yousif Kassab"],
"cfuy7ez3jjepz46guxf2al6r":["yourmanebitch","Kassy"],
"f22ucbl7jpxuzb4tgsywndud":["yo4no2kasa","芳野 嗣 Yoshino Tsukasa"],
"yaztjdxedaxyztyngvziflox":["yourgreekgoddess","Kassandra of Sparta"],
"rrvcgykphqabrztrxhitkcm7":["yumi-kasai","Yumi Kasai"],
"bjz3qnshcovoivduih6fcc5i":["zarinakasil","Zarina Kasil"],
"ekyl24adz5qtn4x565iijzjz":["zaiaku605","Maia Kasoya"],
"egqhwvobr5uvjwd33kbkxqvo":["zarinakassir","❝❞kassir"],
"zrbb7y57u3vdk2k6rfx7uqoy":["zirowaster","Zahra Kashkaki"],
"ehnkt7jlgtvvj2jds32b4xft":["zi-berlin","Zentralinstitut für die kassenärztliche Versorgung"],
"pmafx7n44lrdq5trjbojifyq":["thomaskass","Thomas Kass"],
"2c5sqsyp6ivtc635zzu4vz3o":["skenderbeu","Gjergj Kastrioti"],
"pee7xqo2rnootep3auirsanj":["kaskyna","Jesu"]
}
